Workbook
Name Slicer_Category: #N/A
Name Slicer_order_year: #N/A
Name Slicer_Region: #N/A
Name Slicer_Segment: #N/A

Sheet Sample - Superstore
A1: Row ID | B1: Order ID | C1: Order Date | D1: Ship Date | E1: Ship Mode | F1: Customer ID | G1: Customer Name | H1: Segment | I1: Country | J1: City | K1: State | L1: Postal Code | M1: Region | N1: Product ID | O1: Category | P1: Sub-Category | Q1: Product Name | R1: Sales | S1: Quantity | T1: Discount | U1: Profit | V1: order month | W1: order year
A2: 1 | B2: CA-2016-152156 | C2: 42682 | D2: 42685 | E2: Second Class | F2: CG-12520 | G2: Claire Gute | H2: Consumer | I2: United States | J2: Henderson | K2: Kentucky | L2: 42420 | M2: South | N2: FUR-BO-10001798 | O2: Furniture | P2: Bookcases | Q2: Bush Somerset Collection Bookcase | R2: 261.96 | S2: 2 | T2: 0 | U2: 41.9136 | V2: =EOMONTH(C2,0) -> 42704 | W2: =YEAR(C2) -> 2016
A3: 2 | B3: CA-2016-152156 | C3: 42682 | D3: 42685 | E3: Second Class | F3: CG-12520 | G3: Claire Gute | H3: Consumer | I3: United States | J3: Henderson | K3: Kentucky | L3: 42420 | M3: South | N3: FUR-CH-10000454 | O3: Furniture | P3: Chairs | Q3: Hon Deluxe Fabric Upholstered Stacking Chairs, Rounded Back | R3: 731.94 | S3: 3 | T3: 0 | U3: 219.582 | V3: =EOMONTH(C3,0) -> 42704 | W3: =YEAR(C3) -> 2016
A4: 3 | B4: CA-2016-138688 | C4: 42533 | D4: 6/16/2016 | E4: Second Class | F4: DV-13045 | G4: Darrin Van Huff | H4: Corporate | I4: United States | J4: Los Angeles | K4: California | L4: 90036 | M4: West | N4: OFF-LA-10000240 | O4: Office Supplies | P4: Labels | Q4: Self-Adhesive Address Labels for Typewriters by Universal | R4: 14.62 | S4: 2 | T4: 0 | U4: 6.8714 | V4: =EOMONTH(C4,0) -> 42551 | W4: =YEAR(C4) -> 2016
A5: 4 | B5: US-2015-108966 | C5: 42288 | D5: 10/18/2015 | E5: Standard Class | F5: SO-20335 | G5: Sean O'Donnell | H5: Consumer | I5: United States | J5: Fort Lauderdale | K5: Florida | L5: 33311 | M5: South | N5: FUR-TA-10000577 | O5: Furniture | P5: Tables | Q5: Bretford CR4500 Series Slim Rectangular Table | R5: 957.5775 | S5: 5 | T5: 0.45 | U5: -383.031 | V5: =EOMONTH(C5,0) -> 42308 | W5: =YEAR(C5) -> 2015
A6: 5 | B6: US-2015-108966 | C6: 42288 | D6: 10/18/2015 | E6: Standard Class | F6: SO-20335 | G6: Sean O'Donnell | H6: Consumer | I6: United States | J6: Fort Lauderdale | K6: Florida | L6: 33311 | M6: South | N6: OFF-ST-10000760 | O6: Office Supplies | P6: Storage | Q6: Eldon Fold 'N Roll Cart System | R6: 22.368 | S6: 2 | T6: 0.2 | U6: 2.5164 | V6: =EOMONTH(C6,0) -> 42308 | W6: =YEAR(C6) -> 2015
A7: 6 | B7: CA-2014-115812 | C7: 41799 | D7: 6/14/2014 | E7: Standard Class | F7: BH-11710 | G7: Brosina Hoffman | H7: Consumer | I7: United States | J7: Los Angeles | K7: California | L7: 90032 | M7: West | N7: FUR-FU-10001487 | O7: Furniture | P7: Furnishings | Q7: Eldon Expressions Wood and Plastic Desk Accessories, Cherry Wood | R7: 48.86 | S7: 7 | T7: 0 | U7: 14.1694 | V7: =EOMONTH(C7,0) -> 41820 | W7: =YEAR(C7) -> 2014
A8: 7 | B8: CA-2014-115812 | C8: 41799 | D8: 6/14/2014 | E8: Standard Class | F8: BH-11710 | G8: Brosina Hoffman | H8: Consumer | I8: United States | J8: Los Angeles | K8: California | L8: 90032 | M8: West | N8: OFF-AR-10002833 | O8: Office Supplies | P8: Art | Q8: Newell 322 | R8: 7.28 | S8: 4 | T8: 0 | U8: 1.9656 | V8: =EOMONTH(C8,0) -> 41820 | W8: =YEAR(C8) -> 2014
A9: 8 | B9: CA-2014-115812 | C9: 41799 | D9: 6/14/2014 | E9: Standard Class | F9: BH-11710 | G9: Brosina Hoffman | H9: Consumer | I9: United States | J9: Los Angeles | K9: California | L9: 90032 | M9: West | N9: TEC-PH-10002275 | O9: Technology | P9: Phones | Q9: Mitel 5320 IP Phone VoIP phone | R9: 907.152 | S9: 6 | T9: 0.2 | U9: 90.7152 | V9: =EOMONTH(C9,0) -> 41820 | W9: =YEAR(C9) -> 2014
A10: 9 | B10: CA-2014-115812 | C10: 41799 | D10: 6/14/2014 | E10: Standard Class | F10: BH-11710 | G10: Brosina Hoffman | H10: Consumer | I10: United States | J10: Los Angeles | K10: California | L10: 90032 | M10: West | N10: OFF-BI-10003910 | O10: Office Supplies | P10: Binders | Q10: DXL Angle-View Binders with Locking Rings by Samsill | R10: 18.504 | S10: 3 | T10: 0.2 | U10: 5.7825 | V10: =EOMONTH(C10,0) -> 41820 | W10: =YEAR(C10) -> 2014
A11: 10 | B11: CA-2014-115812 | C11: 41799 | D11: 6/14/2014 | E11: Standard Class | F11: BH-11710 | G11: Brosina Hoffman | H11: Consumer | I11: United States | J11: Los Angeles | K11: California | L11: 90032 | M11: West | N11: OFF-AP-10002892 | O11: Office Supplies | P11: Appliances | Q11: Belkin F5C206VTEL 6 Outlet Surge | R11: 114.9 | S11: 5 | T11: 0 | U11: 34.47 | V11: =EOMONTH(C11,0) -> 41820 | W11: =YEAR(C11) -> 2014
A12: 11 | B12: CA-2014-115812 | C12: 41799 | D12: 6/14/2014 | E12: Standard Class | F12: BH-11710 | G12: Brosina Hoffman | H12: Consumer | I12: United States | J12: Los Angeles | K12: California | L12: 90032 | M12: West | N12: FUR-TA-10001539 | O12: Furniture | P12: Tables | Q12: Chromcraft Rectangular Conference Tables | R12: 1706.184 | S12: 9 | T12: 0.2 | U12: 85.3092 | V12: =EOMONTH(C12,0) -> 41820 | W12: =YEAR(C12) -> 2014
A13: 12 | B13: CA-2014-115812 | C13: 41799 | D13: 6/14/2014 | E13: Standard Class | F13: BH-11710 | G13: Brosina Hoffman | H13: Consumer | I13: United States | J13: Los Angeles | K13: California | L13: 90032 | M13: West | N13: TEC-PH-10002033 | O13: Technology | P13: Phones | Q13: Konftel 250 Conference†phone†- Charcoal black | R13: 911.424 | S13: 4 | T13: 0.2 | U13: 68.3568 | V13: =EOMONTH(C13,0) -> 41820 | W13: =YEAR(C13) -> 2014
A14: 13 | B14: CA-2017-114412 | C14: 42840 | D14: 4/20/2017 | E14: Standard Class | F14: AA-10480 | G14: Andrew Allen | H14: Consumer | I14: United States | J14: Concord | K14: North Carolina | L14: 28027 | M14: South | N14: OFF-PA-10002365 | O14: Office Supplies | P14: Paper | Q14: Xerox 1967 | R14: 15.552 | S14: 3 | T14: 0.2 | U14: 5.4432 | V14: =EOMONTH(C14,0) -> 42855 | W14: =YEAR(C14) -> 2017
A15: 14 | B15: CA-2016-161389 | C15: 42709 | D15: 42655 | E15: Standard Class | F15: IM-15070 | G15: Irene Maddox | H15: Consumer | I15: United States | J15: Seattle | K15: Washington | L15: 98103 | M15: West | N15: OFF-BI-10003656 | O15: Office Supplies | P15: Binders | Q15: Fellowes PB200 Plastic Comb Binding Machine | R15: 407.976 | S15: 3 | T15: 0.2 | U15: 132.5922 | V15: =EOMONTH(C15,0) -> 42735 | W15: =YEAR(C15) -> 2016
A16: 15 | B16: US-2015-118983 | C16: 42330 | D16: 11/26/2015 | E16: Standard Class | F16: HP-14815 | G16: Harold Pawlan | H16: Home Office | I16: United States | J16: Fort Worth | K16: Texas | L16: 76106 | M16: Central | N16: OFF-AP-10002311 | O16: Office Supplies | P16: Appliances | Q16: Holmes Replacement Filter for HEPA Air Cleaner, Very Large Room, HEPA Filter | R16: 68.81 | S16: 5 | T16: 0.8 | U16: -123.858 | V16: =EOMONTH(C16,0) -> 42338 | W16: =YEAR(C16) -> 2015
A17: 16 | B17: US-2015-118983 | C17: 42330 | D17: 11/26/2015 | E17: Standard Class | F17: HP-14815 | G17: Harold Pawlan | H17: Home Office | I17: United States | J17: Fort Worth | K17: Texas | L17: 76106 | M17: Central | N17: OFF-BI-10000756 | O17: Office Supplies | P17: Binders | Q17: Storex DuraTech Recycled Plastic Frosted Binders | R17: 2.544 | S17: 3 | T17: 0.8 | U17: -3.816 | V17: =EOMONTH(C17,0) -> 42338 | W17: =YEAR(C17) -> 2015
A18: 17 | B18: CA-2014-105893 | C18: 41954 | D18: 11/18/2014 | E18: Standard Class | F18: PK-19075 | G18: Pete Kriz | H18: Consumer | I18: United States | J18: Madison | K18: Wisconsin | L18: 53711 | M18: Central | N18: OFF-ST-10004186 | O18: Office Supplies | P18: Storage | Q18: Stur-D-Stor Shelving, Vertical 5-Shelf: 72"H x 36"W x 18 1/2"D | R18: 665.88 | S18: 6 | T18: 0 | U18: 13.3176 | V18: =EOMONTH(C18,0) -> 41973 | W18: =YEAR(C18) -> 2014
A19: 18 | B19: CA-2014-167164 | C19: 41772 | D19: 5/15/2014 | E19: Second Class | F19: AG-10270 | G19: Alejandro Grove | H19: Consumer | I19: United States | J19: West Jordan | K19: Utah | L19: 84084 | M19: West | N19: OFF-ST-10000107 | O19: Office Supplies | P19: Storage | Q19: Fellowes Super Stor/Drawer | R19: 55.5 | S19: 2 | T19: 0 | U19: 9.99 | V19: =EOMONTH(C19,0) -> 41790 | W19: =YEAR(C19) -> 2014
A20: 19 | B20: CA-2014-143336 | C20: 41878 | D20: 41648 | E20: Second Class | F20: ZD-21925 | G20: Zuschuss Donatelli | H20: Consumer | I20: United States | J20: San Francisco | K20: California | L20: 94109 | M20: West | N20: OFF-AR-10003056 | O20: Office Supplies | P20: Art | Q20: Newell 341 | R20: 8.56 | S20: 2 | T20: 0 | U20: 2.4824 | V20: =EOMONTH(C20,0) -> 41882 | W20: =YEAR(C20) -> 2014
A21: 20 | B21: CA-2014-143336 | C21: 41878 | D21: 41648 | E21: Second Class | F21: ZD-21925 | G21: Zuschuss Donatelli | H21: Consumer | I21: United States | J21: San Francisco | K21: California | L21: 94109 | M21: West | N21: TEC-PH-10001949 | O21: Technology | P21: Phones | Q21: Cisco SPA 501G IP Phone | R21: 213.48 | S21: 3 | T21: 0.2 | U21: 16.011 | V21: =EOMONTH(C21,0) -> 41882 | W21: =YEAR(C21) -> 2014
A22: 21 | B22: CA-2014-143336 | C22: 41878 | D22: 41648 | E22: Second Class | F22: ZD-21925 | G22: Zuschuss Donatelli | H22: Consumer | I22: United States | J22: San Francisco | K22: California | L22: 94109 | M22: West | N22: OFF-BI-10002215 | O22: Office Supplies | P22: Binders | Q22: Wilson Jones Hanging View Binder, White, 1" | R22: 22.72 | S22: 4 | T22: 0.2 | U22: 7.384 | V22: =EOMONTH(C22,0) -> 41882 | W22: =YEAR(C22) -> 2014
A23: 22 | B23: CA-2016-137330 | C23: 42713 | D23: 12/13/2016 | E23: Standard Class | F23: KB-16585 | G23: Ken Black | H23: Corporate | I23: United States | J23: Fremont | K23: Nebraska | L23: 68025 | M23: Central | N23: OFF-AR-10000246 | O23: Office Supplies | P23: Art | Q23: Newell 318 | R23: 19.46 | S23: 7 | T23: 0 | U23: 5.0596 | V23: =EOMONTH(C23,0) -> 42735 | W23: =YEAR(C23) -> 2016
A24: 23 | B24: CA-2016-137330 | C24: 42713 | D24: 12/13/2016 | E24: Standard Class | F24: KB-16585 | G24: Ken Black | H24: Corporate | I24: United States | J24: Fremont | K24: Nebraska | L24: 68025 | M24: Central | N24: OFF-AP-10001492 | O24: Office Supplies | P24: Appliances | Q24: Acco Six-Outlet Power Strip, 4' Cord Length | R24: 60.34 | S24: 7 | T24: 0 | U24: 15.6884 | V24: =EOMONTH(C24,0) -> 42735 | W24: =YEAR(C24) -> 2016
A25: 24 | B25: US-2017-156909 | C25: 42932 | D25: 7/18/2017 | E25: Second Class | F25: SF-20065 | G25: Sandra Flanagan | H25: Consumer | I25: United States | J25: Philadelphia | K25: Pennsylvania | L25: 19140 | M25: East | N25: FUR-CH-10002774 | O25: Furniture | P25: Chairs | Q25: Global Deluxe Stacking Chair, Gray | R25: 71.372 | S25: 2 | T25: 0.3 | U25: -1.0196 | V25: =EOMONTH(C25,0) -> 42947 | W25: =YEAR(C25) -> 2017
A26: 25 | B26: CA-2015-106320 | C26: 42272 | D26: 9/30/2015 | E26: Standard Class | F26: EB-13870 | G26: Emily Burns | H26: Consumer | I26: United States | J26: Orem | K26: Utah | L26: 84057 | M26: West | N26: FUR-TA-10000577 | O26: Furniture | P26: Tables | Q26: Bretford CR4500 Series Slim Rectangular Table | R26: 1044.63 | S26: 3 | T26: 0 | U26: 240.2649 | V26: =EOMONTH(C26,0) -> 42277 | W26: =YEAR(C26) -> 2015
A27: 26 | B27: CA-2016-121755 | C27: 42385 | D27: 1/20/2016 | E27: Second Class | F27: EH-13945 | G27: Eric Hoffmann | H27: Consumer | I27: United States | J27: Los Angeles | K27: California | L27: 90049 | M27: West | N27: OFF-BI-10001634 | O27: Office Supplies | P27: Binders | Q27: Wilson Jones Active Use Binders | R27: 11.648 | S27: 2 | T27: 0.2 | U27: 4.2224 | V27: =EOMONTH(C27,0) -> 42400 | W27: =YEAR(C27) -> 2016
A28: 27 | B28: CA-2016-121755 | C28: 42385 | D28: 1/20/2016 | E28: Second Class | F28: EH-13945 | G28: Eric Hoffmann | H28: Consumer | I28: United States | J28: Los Angeles | K28: California | L28: 90049 | M28: West | N28: TEC-AC-10003027 | O28: Technology | P28: Accessories | Q28: Imation†8GB Mini TravelDrive USB 2.0†Flash Drive | R28: 90.57 | S28: 3 | T28: 0 | U28: 11.7741 | V28: =EOMONTH(C28,0) -> 42400 | W28: =YEAR(C28) -> 2016
A29: 28 | B29: US-2015-150630 | C29: 42264 | D29: 9/21/2015 | E29: Standard Class | F29: TB-21520 | G29: Tracy Blumstein | H29: Consumer | I29: United States | J29: Philadelphia | K29: Pennsylvania | L29: 19140 | M29: East | N29: FUR-BO-10004834 | O29: Furniture | P29: Bookcases | Q29: Riverside Palais Royal Lawyers Bookcase, Royale Cherry Finish | R29: 3083.43 | S29: 7 | T29: 0.5 | U29: -1665.0522 | V29: =EOMONTH(C29,0) -> 42277 | W29: =YEAR(C29) -> 2015
A30: 29 | B30: US-2015-150630 | C30: 42264 | D30: 9/21/2015 | E30: Standard Class | F30: TB-21520 | G30: Tracy Blumstein | H30: Consumer | I30: United States | J30: Philadelphia | K30: Pennsylvania | L30: 19140 | M30: East | N30: OFF-BI-10000474 | O30: Office Supplies | P30: Binders | Q30: Avery Recycled Flexi-View Covers for Binding Systems | R30: 9.618 | S30: 2 | T30: 0.7 | U30: -7.0532 | V30: =EOMONTH(C30,0) -> 42277 | W30: =YEAR(C30) -> 2015
A31: 30 | B31: US-2015-150630 | C31: 42264 | D31: 9/21/2015 | E31: Standard Class | F31: TB-21520 | G31: Tracy Blumstein | H31: Consumer | I31: United States | J31: Philadelphia | K31: Pennsylvania | L31: 19140 | M31: East | N31: FUR-FU-10004848 | O31: Furniture | P31: Furnishings | Q31: Howard Miller 13-3/4" Diameter Brushed Chrome Round Wall Clock | R31: 124.2 | S31: 3 | T31: 0.2 | U31: 15.525 | V31: =EOMONTH(C31,0) -> 42277 | W31: =YEAR(C31) -> 2015
A32: 31 | B32: US-2015-150630 | C32: 42264 | D32: 9/21/2015 | E32: Standard Class | F32: TB-21520 | G32: Tracy Blumstein | H32: Consumer | I32: United States | J32: Philadelphia | K32: Pennsylvania | L32: 19140 | M32: East | N32: OFF-EN-10001509 | O32: Office Supplies | P32: Envelopes | Q32: Poly String Tie Envelopes | R32: 3.264 | S32: 2 | T32: 0.2 | U32: 1.1016 | V32: =EOMONTH(C32,0) -> 42277 | W32: =YEAR(C32) -> 2015
A33: 32 | B33: US-2015-150630 | C33: 42264 | D33: 9/21/2015 | E33: Standard Class | F33: TB-21520 | G33: Tracy Blumstein | H33: Consumer | I33: United States | J33: Philadelphia | K33: Pennsylvania | L33: 19140 | M33: East | N33: OFF-AR-10004042 | O33: Office Supplies | P33: Art | Q33: BOSTON Model 1800 Electric Pencil Sharpeners, Putty/Woodgrain | R33: 86.304 | S33: 6 | T33: 0.2 | U33: 9.7092 | V33: =EOMONTH(C33,0) -> 42277 | W33: =YEAR(C33) -> 2015
A34: 33 | B34: US-2015-150630 | C34: 42264 | D34: 9/21/2015 | E34: Standard Class | F34: TB-21520 | G34: Tracy Blumstein | H34: Consumer | I34: United States | J34: Philadelphia | K34: Pennsylvania | L34: 19140 | M34: East | N34: OFF-BI-10001525 | O34: Office Supplies | P34: Binders | Q34: Acco Pressboard Covers with Storage Hooks, 14 7/8" x 11", Executive Red | R34: 6.858 | S34: 6 | T34: 0.7 | U34: -5.715 | V34: =EOMONTH(C34,0) -> 42277 | W34: =YEAR(C34) -> 2015
... A36: 35 | B36: CA-2017-107727 | C36: 43027 | D36: 10/23/2017 | E36: Second Class | F36: MA-17560 | G36: Matt Abelman | H36: Home Office | I36: United States | J36: Houston | K36: Texas | L36: 77095 | M36: Central | N36: OFF-PA-10000249 | O36: Office Supplies | P36: Paper | Q36: Easy-staple paper | R36: 29.472 | S36: 3 | T36: 0.2 | U36: 9.9468 | V36: =EOMONTH(C36,0) -> 43039 | W36: =YEAR(C36) -> 2017
A37: 36 | B37: CA-2016-117590 | C37: 42712 | D37: 42655 | E37: First Class | F37: GH-14485 | G37: Gene Hale | H37: Corporate | I37: United States | J37: Richardson | K37: Texas | L37: 75080 | M37: Central | N37: TEC-PH-10004977 | O37: Technology | P37: Phones | Q37: GE 30524EE4 | R37: 1097.544 | S37: 7 | T37: 0.2 | U37: 123.4737 | V37: =EOMONTH(C37,0) -> 42735 | W37: =YEAR(C37) -> 2016
A38: 37 | B38: CA-2016-117590 | C38: 42712 | D38: 42655 | E38: First Class | F38: GH-14485 | G38: Gene Hale | H38: Corporate | I38: United States | J38: Richardson | K38: Texas | L38: 75080 | M38: Central | N38: FUR-FU-10003664 | O38: Furniture | P38: Furnishings | Q38: Electrix Architect's Clamp-On Swing Arm Lamp, Black | R38: 190.92 | S38: 5 | T38: 0.6 | U38: -147.963 | V38: =EOMONTH(C38,0) -> 42735 | W38: =YEAR(C38) -> 2016
A39: 38 | B39: CA-2015-117415 | C39: 42365 | D39: 12/31/2015 | E39: Standard Class | F39: SN-20710 | G39: Steve Nguyen | H39: Home Office | I39: United States | J39: Houston | K39: Texas | L39: 77041 | M39: Central | N39: OFF-EN-10002986 | O39: Office Supplies | P39: Envelopes | Q39: #10-4 1/8" x 9 1/2" Premium Diagonal Seam Envelopes | R39: 113.328 | S39: 9 | T39: 0.2 | U39: 35.415 | V39: =EOMONTH(C39,0) -> 42369 | W39: =YEAR(C39) -> 2015
A40: 39 | B40: CA-2015-117415 | C40: 42365 | D40: 12/31/2015 | E40: Standard Class | F40: SN-20710 | G40: Steve Nguyen | H40: Home Office | I40: United States | J40: Houston | K40: Texas | L40: 77041 | M40: Central | N40: FUR-BO-10002545 | O40: Furniture | P40: Bookcases | Q40: Atlantic Metals Mobile 3-Shelf Bookcases, Custom Colors | R40: 532.3992 | S40: 3 | T40: 0.32 | U40: -46.9764 | V40: =EOMONTH(C40,0) -> 42369 | W40: =YEAR(C40) -> 2015
A41: 40 | B41: CA-2015-117415 | C41: 42365 | D41: 12/31/2015 | E41: Standard Class | F41: SN-20710 | G41: Steve Nguyen | H41: Home Office | I41: United States | J41: Houston | K41: Texas | L41: 77041 | M41: Central | N41: FUR-CH-10004218 | O41: Furniture | P41: Chairs | Q41: Global Fabric Manager's Chair, Dark Gray | R41: 212.058 | S41: 3 | T41: 0.3 | U41: -15.147 | V41: =EOMONTH(C41,0) -> 42369 | W41: =YEAR(C41) -> 2015
A42: 41 | B42: CA-2015-117415 | C42: 42365 | D42: 12/31/2015 | E42: Standard Class | F42: SN-20710 | G42: Steve Nguyen | H42: Home Office | I42: United States | J42: Houston | K42: Texas | L42: 77041 | M42: Central | N42: TEC-PH-10000486 | O42: Technology | P42: Phones | Q42: Plantronics HL10 Handset Lifter | R42: 371.168 | S42: 4 | T42: 0.2 | U42: 41.7564 | V42: =EOMONTH(C42,0) -> 42369 | W42: =YEAR(C42) -> 2015
A43: 42 | B43: CA-2017-120999 | C43: 42988 | D43: 9/15/2017 | E43: Standard Class | F43: LC-16930 | G43: Linda Cazamias | H43: Corporate | I43: United States | J43: Naperville | K43: Illinois | L43: 60540 | M43: Central | N43: TEC-PH-10004093 | O43: Technology | P43: Phones | Q43: Panasonic Kx-TS550 | R43: 147.168 | S43: 4 | T43: 0.2 | U43: 16.5564 | V43: =EOMONTH(C43,0) -> 43008 | W43: =YEAR(C43) -> 2017
A44: 43 | B44: CA-2016-101343 | C44: 42568 | D44: 7/22/2016 | E44: Standard Class | F44: RA-19885 | G44: Ruben Ausman | H44: Corporate | I44: United States | J44: Los Angeles | K44: California | L44: 90049 | M44: West | N44: OFF-ST-10003479 | O44: Office Supplies | P44: Storage | Q44: Eldon Base for stackable storage shelf, platinum | R44: 77.88 | S44: 2 | T44: 0 | U44: 3.894 | V44: =EOMONTH(C44,0) -> 42582 | W44: =YEAR(C44) -> 2016
A45: 44 | B45: CA-2017-139619 | C45: 42997 | D45: 9/23/2017 | E45: Standard Class | F45: ES-14080 | G45: Erin Smith | H45: Corporate | I45: United States | J45: Melbourne | K45: Florida | L45: 32935 | M45: South | N45: OFF-ST-10003282 | O45: Office Supplies | P45: Storage | Q45: Advantus 10-Drawer Portable Organizer, Chrome Metal Frame, Smoke Drawers | R45: 95.616 | S45: 2 | T45: 0.2 | U45: 9.5616 | V45: =EOMONTH(C45,0) -> 43008 | W45: =YEAR(C45) -> 2017
A46: 45 | B46: CA-2016-118255 | C46: 42440 | D46: 3/13/2016 | E46: First Class | F46: ON-18715 | G46: Odella Nelson | H46: Corporate | I46: United States | J46: Eagan | K46: Minnesota | L46: 55122 | M46: Central | N46: TEC-AC-10000171 | O46: Technology | P46: Accessories | Q46: Verbatim 25 GB 6x Blu-ray Single Layer Recordable Disc, 25/Pack | R46: 45.98 | S46: 2 | T46: 0 | U46: 19.7714 | V46: =EOMONTH(C46,0) -> 42460 | W46: =YEAR(C46) -> 2016
A47: 46 | B47: CA-2016-118255 | C47: 42440 | D47: 3/13/2016 | E47: First Class | F47: ON-18715 | G47: Odella Nelson | H47: Corporate | I47: United States | J47: Eagan | K47: Minnesota | L47: 55122 | M47: Central | N47: OFF-BI-10003291 | O47: Office Supplies | P47: Binders | Q47: Wilson Jones Leather-Like Binders with DublLock Round Rings | R47: 17.46 | S47: 2 | T47: 0 | U47: 8.2062 | V47: =EOMONTH(C47,0) -> 42460 | W47: =YEAR(C47) -> 2016
A48: 47 | B48: CA-2014-146703 | C48: 41932 | D48: 10/25/2014 | E48: Second Class | F48: PO-18865 | G48: Patrick O'Donnell | H48: Consumer | I48: United States | J48: Westland | K48: Michigan | L48: 48185 | M48: Central | N48: OFF-ST-10001713 | O48: Office Supplies | P48: Storage | Q48: Gould Plastics 9-Pocket Panel Bin, 18-3/8w x 5-1/4d x 20-1/2h, Black | R48: 211.96 | S48: 4 | T48: 0 | U48: 8.4784 | V48: =EOMONTH(C48,0) -> 41943 | W48: =YEAR(C48) -> 2014
A49: 48 | B49: CA-2016-169194 | C49: 42541 | D49: 6/25/2016 | E49: Standard Class | F49: LH-16900 | G49: Lena Hernandez | H49: Consumer | I49: United States | J49: Dover | K49: Delaware | L49: 19901 | M49: East | N49: TEC-AC-10002167 | O49: Technology | P49: Accessories | Q49: Imation†8gb Micro Traveldrive Usb 2.0†Flash Drive | R49: 45 | S49: 3 | T49: 0 | U49: 4.95 | V49: =EOMONTH(C49,0) -> 42551 | W49: =YEAR(C49) -> 2016
A50: 49 | B50: CA-2016-169194 | C50: 42541 | D50: 6/25/2016 | E50: Standard Class | F50: LH-16900 | G50: Lena Hernandez | H50: Consumer | I50: United States | J50: Dover | K50: Delaware | L50: 19901 | M50: East | N50: TEC-PH-10003988 | O50: Technology | P50: Phones | Q50: LF Elite 3D Dazzle Designer Hard Case Cover, Lf Stylus Pen and Wiper For Apple Iphone 5c Mini Lite | R50: 21.8 | S50: 2 | T50: 0 | U50: 6.104 | V50: =EOMONTH(C50,0) -> 42551 | W50: =YEAR(C50) -> 2016
... A67: 66 | B67: CA-2015-135545 | C67: 42332 | D67: 11/30/2015 | E67: Standard Class | F67: KM-16720 | G67: Kunst Miller | H67: Consumer | I67: United States | J67: Los Angeles | K67: California | L67: 90004 | M67: West | N67: FUR-FU-10000397 | O67: Furniture | P67: Furnishings | Q67: Luxo Economy Swing Arm Lamp | R67: 79.76 | S67: 4 | T67: 0 | U67: 22.3328 | V67: =EOMONTH(C67,0) -> 42338 | W67: =YEAR(C67) -> 2015
A68: 67 | B68: US-2015-164175 | C68: 42124 | D68: 42129 | E68: Standard Class | F68: PS-18970 | G68: Paul Stevenson | H68: Home Office | I68: United States | J68: Chicago | K68: Illinois | L68: 60610 | M68: Central | N68: FUR-CH-10001146 | O68: Furniture | P68: Chairs | Q68: Global Value Mid-Back Manager's Chair, Gray | R68: 213.115 | S68: 5 | T68: 0.3 | U68: -15.2225 | V68: =EOMONTH(C68,0) -> 42124 | W68: =YEAR(C68) -> 2015
A69: 68 | B69: CA-2014-106376 | C69: 41978 | D69: 41924 | E69: Standard Class | F69: BS-11590 | G69: Brendan Sweed | H69: Corporate | I69: United States | J69: Gilbert | K69: Arizona | L69: 85234 | M69: West | N69: OFF-AR-10002671 | O69: Office Supplies | P69: Art | Q69: Hunt BOSTON Model 1606 High-Volume Electric Pencil Sharpener, Beige | R69: 1113.024 | S69: 8 | T69: 0.2 | U69: 111.3024 | V69: =EOMONTH(C69,0) -> 42004 | W69: =YEAR(C69) -> 2014
A70: 69 | B70: CA-2014-106376 | C70: 41978 | D70: 41924 | E70: Standard Class | F70: BS-11590 | G70: Brendan Sweed | H70: Corporate | I70: United States | J70: Gilbert | K70: Arizona | L70: 85234 | M70: West | N70: TEC-PH-10002726 | O70: Technology | P70: Phones | Q70: netTALK DUO VoIP Telephone Service | R70: 167.968 | S70: 4 | T70: 0.2 | U70: 62.988 | V70: =EOMONTH(C70,0) -> 42004 | W70: =YEAR(C70) -> 2014
A71: 70 | B71: CA-2016-119823 | C71: 42525 | D71: 42527 | E71: First Class | F71: KD-16270 | G71: Karen Daniels | H71: Consumer | I71: United States | J71: Springfield | K71: Virginia | L71: 22153 | M71: South | N71: OFF-PA-10000482 | O71: Office Supplies | P71: Paper | Q71: Snap-A-Way Black Print Carbonless Ruled Speed Letter, Triplicate | R71: 75.88 | S71: 2 | T71: 0 | U71: 35.6636 | V71: =EOMONTH(C71,0) -> 42551 | W71: =YEAR(C71) -> 2016
A72: 71 | B72: CA-2016-106075 | C72: 42631 | D72: 9/23/2016 | E72: Standard Class | F72: HM-14980 | G72: Henry MacAllister | H72: Consumer | I72: United States | J72: New York City | K72: New York | L72: 10009 | M72: East | N72: OFF-BI-10004654 | O72: Office Supplies | P72: Binders | Q72: Avery Binding System Hidden Tab Executive Style Index Sets | R72: 4.616 | S72: 1 | T72: 0.2 | U72: 1.731 | V72: =EOMONTH(C72,0) -> 42643 | W72: =YEAR(C72) -> 2016
A73: 72 | B73: CA-2017-114440 | C73: 42992 | D73: 9/17/2017 | E73: Second Class | F73: TB-21520 | G73: Tracy Blumstein | H73: Consumer | I73: United States | J73: Jackson | K73: Michigan | L73: 49201 | M73: Central | N73: OFF-PA-10004675 | O73: Office Supplies | P73: Paper | Q73: Telephone Message Books with Fax/Mobile Section, 5 1/2" x 3 3/16" | R73: 19.05 | S73: 3 | T73: 0 | U73: 8.763 | V73: =EOMONTH(C73,0) -> 43008 | W73: =YEAR(C73) -> 2017
A74: 73 | B74: US-2015-134026 | C74: 42120 | D74: 42040 | E74: Standard Class | F74: JE-15745 | G74: Joel Eaton | H74: Consumer | I74: United States | J74: Memphis | K74: Tennessee | L74: 38109 | M74: South | N74: FUR-CH-10000513 | O74: Furniture | P74: Chairs | Q74: High-Back Leather Manager's Chair | R74: 831.936 | S74: 8 | T74: 0.2 | U74: -114.3912 | V74: =EOMONTH(C74,0) -> 42124 | W74: =YEAR(C74) -> 2015
A75: 74 | B75: US-2015-134026 | C75: 42120 | D75: 42040 | E75: Standard Class | F75: JE-15745 | G75: Joel Eaton | H75: Consumer | I75: United States | J75: Memphis | K75: Tennessee | L75: 38109 | M75: South | N75: FUR-FU-10003708 | O75: Furniture | P75: Furnishings | Q75: Tenex Traditional Chairmats for Medium Pile Carpet, Standard Lip, 36" x 48" | R75: 97.04 | S75: 2 | T75: 0.2 | U75: 1.213 | V75: =EOMONTH(C75,0) -> 42124 | W75: =YEAR(C75) -> 2015
A76: 75 | B76: US-2015-134026 | C76: 42120 | D76: 42040 | E76: Standard Class | F76: JE-15745 | G76: Joel Eaton | H76: Consumer | I76: United States | J76: Memphis | K76: Tennessee | L76: 38109 | M76: South | N76: OFF-ST-10004123 | O76: Office Supplies | P76: Storage | Q76: Safco Industrial Wire Shelving System | R76: 72.784 | S76: 1 | T76: 0.2 | U76: -18.196 | V76: =EOMONTH(C76,0) -> 42124 | W76: =YEAR(C76) -> 2015
A77: 76 | B77: US-2017-118038 | C77: 43078 | D77: 43051 | E77: First Class | F77: KB-16600 | G77: Ken Brennan | H77: Corporate | I77: United States | J77: Houston | K77: Texas | L77: 77041 | M77: Central | N77: OFF-BI-10004182 | O77: Office Supplies | P77: Binders | Q77: Economy Binders | R77: 1.248 | S77: 3 | T77: 0.8 | U77: -1.9344 | V77: =EOMONTH(C77,0) -> 43100 | W77: =YEAR(C77) -> 2017
A78: 77 | B78: US-2017-118038 | C78: 43078 | D78: 43051 | E78: First Class | F78: KB-16600 | G78: Ken Brennan | H78: Corporate | I78: United States | J78: Houston | K78: Texas | L78: 77041 | M78: Central | N78: FUR-FU-10000260 | O78: Furniture | P78: Furnishings | Q78: 6" Cubicle Wall Clock, Black | R78: 9.708 | S78: 3 | T78: 0.6 | U78: -5.8248 | V78: =EOMONTH(C78,0) -> 43100 | W78: =YEAR(C78) -> 2017
A79: 78 | B79: US-2017-118038 | C79: 43078 | D79: 43051 | E79: First Class | F79: KB-16600 | G79: Ken Brennan | H79: Corporate | I79: United States | J79: Houston | K79: Texas | L79: 77041 | M79: Central | N79: OFF-ST-10000615 | O79: Office Supplies | P79: Storage | Q79: SimpliFile Personal File, Black Granite, 15w x 6-15/16d x 11-1/4h | R79: 27.24 | S79: 3 | T79: 0.2 | U79: 2.724 | V79: =EOMONTH(C79,0) -> 43100 | W79: =YEAR(C79) -> 2017
A80: 79 | B80: US-2014-147606 | C80: 41969 | D80: 41651 | E80: Second Class | F80: JE-15745 | G80: Joel Eaton | H80: Consumer | I80: United States | J80: Houston | K80: Texas | L80: 77070 | M80: Central | N80: FUR-FU-10003194 | O80: Furniture | P80: Furnishings | Q80: Eldon Expressions Desk Accessory, Wood Pencil Holder, Oak | R80: 19.3 | S80: 5 | T80: 0.6 | U80: -14.475 | V80: =EOMONTH(C80,0) -> 41973 | W80: =YEAR(C80) -> 2014
A81: 80 | B81: CA-2016-127208 | C81: 42533 | D81: 6/15/2016 | E81: First Class | F81: SC-20770 | G81: Stewart Carmichael | H81: Corporate | I81: United States | J81: Decatur | K81: Alabama | L81: 35601 | M81: South | N81: OFF-AP-10002118 | O81: Office Supplies | P81: Appliances | Q81: 1.7 Cubic Foot Compact "Cube" Office Refrigerators | R81: 208.16 | S81: 1 | T81: 0 | U81: 56.2032 | V81: =EOMONTH(C81,0) -> 42551 | W81: =YEAR(C81) -> 2016
A82: 81 | B82: CA-2016-127208 | C82: 42533 | D82: 6/15/2016 | E82: First Class | F82: SC-20770 | G82: Stewart Carmichael | H82: Corporate | I82: United States | J82: Decatur | K82: Alabama | L82: 35601 | M82: South | N82: OFF-BI-10002309 | O82: Office Supplies | P82: Binders | Q82: Avery Heavy-Duty EZD Binder With Locking Rings | R82: 16.74 | S82: 3 | T82: 0 | U82: 8.0352 | V82: =EOMONTH(C82,0) -> 42551 | W82: =YEAR(C82) -> 2016
A83: 82 | B83: CA-2014-139451 | C83: 41924 | D83: 10/16/2014 | E83: Standard Class | F83: DN-13690 | G83: Duane Noonan | H83: Consumer | I83: United States | J83: San Francisco | K83: California | L83: 94122 | M83: West | N83: OFF-AR-10002053 | O83: Office Supplies | P83: Art | Q83: Premium Writing Pencils, Soft, #2 by Central Association for the Blind | R83: 14.9 | S83: 5 | T83: 0 | U83: 4.172 | V83: =EOMONTH(C83,0) -> 41943 | W83: =YEAR(C83) -> 2014
A84: 83 | B84: CA-2014-139451 | C84: 41924 | D84: 10/16/2014 | E84: Standard Class | F84: DN-13690 | G84: Duane Noonan | H84: Consumer | I84: United States | J84: San Francisco | K84: California | L84: 94122 | M84: West | N84: OFF-ST-10002370 | O84: Office Supplies | P84: Storage | Q84: Sortfiler Multipurpose Personal File Organizer, Black | R84: 21.39 | S84: 1 | T84: 0 | U84: 6.2031 | V84: =EOMONTH(C84,0) -> 41943 | W84: =YEAR(C84) -> 2014
A85: 84 | B85: CA-2015-149734 | C85: 42250 | D85: 42225 | E85: Standard Class | F85: JC-16105 | G85: Julie Creighton | H85: Corporate | I85: United States | J85: Durham | K85: North Carolina | L85: 27707 | M85: South | N85: OFF-EN-10000927 | O85: Office Supplies | P85: Envelopes | Q85: Jet-Pak Recycled Peel 'N' Seal Padded Mailers | R85: 200.984 | S85: 7 | T85: 0.2 | U85: 62.8075 | V85: =EOMONTH(C85,0) -> 42277 | W85: =YEAR(C85) -> 2015
A86: 85 | B86: US-2017-119662 | C86: 43052 | D86: 11/16/2017 | E86: First Class | F86: CS-12400 | G86: Christopher Schild | H86: Home Office | I86: United States | J86: Chicago | K86: Illinois | L86: 60623 | M86: Central | N86: OFF-ST-10003656 | O86: Office Supplies | P86: Storage | Q86: Safco Industrial Wire Shelving | R86: 230.376 | S86: 3 | T86: 0.2 | U86: -48.9549 | V86: =EOMONTH(C86,0) -> 43069 | W86: =YEAR(C86) -> 2017
A87: 86 | B87: CA-2017-140088 | C87: 42883 | D87: 5/30/2017 | E87: Second Class | F87: PO-18865 | G87: Patrick O'Donnell | H87: Consumer | I87: United States | J87: Columbia | K87: South Carolina | L87: 29203 | M87: South | N87: FUR-CH-10000863 | O87: Furniture | P87: Chairs | Q87: Novimex Swivel Fabric Task Chair | R87: 301.96 | S87: 2 | T87: 0 | U87: 33.2156 | V87: =EOMONTH(C87,0) -> 42886 | W87: =YEAR(C87) -> 2017
A88: 87 | B88: CA-2017-155558 | C88: 43034 | D88: 42777 | E88: Standard Class | F88: PG-18895 | G88: Paul Gonzalez | H88: Consumer | I88: United States | J88: Rochester | K88: Minnesota | L88: 55901 | M88: Central | N88: TEC-AC-10001998 | O88: Technology | P88: Accessories | Q88: Logitech†LS21 Speaker System - PC Multimedia - 2.1-CH - Wired | R88: 19.99 | S88: 1 | T88: 0 | U88: 6.7966 | V88: =EOMONTH(C88,0) -> 43039 | W88: =YEAR(C88) -> 2017
A89: 88 | B89: CA-2017-155558 | C89: 43034 | D89: 42777 | E89: Standard Class | F89: PG-18895 | G89: Paul Gonzalez | H89: Consumer | I89: United States | J89: Rochester | K89: Minnesota | L89: 55901 | M89: Central | N89: OFF-LA-10000134 | O89: Office Supplies | P89: Labels | Q89: Avery 511 | R89: 6.16 | S89: 2 | T89: 0 | U89: 2.9568 | V89: =EOMONTH(C89,0) -> 43039 | W89: =YEAR(C89) -> 2017
A90: 89 | B90: CA-2016-159695 | C90: 42465 | D90: 42647 | E90: Second Class | F90: GM-14455 | G90: Gary Mitchum | H90: Home Office | I90: United States | J90: Houston | K90: Texas | L90: 77095 | M90: Central | N90: OFF-ST-10003442 | O90: Office Supplies | P90: Storage | Q90: Eldon Portable Mobile Manager | R90: 158.368 | S90: 7 | T90: 0.2 | U90: 13.8572 | V90: =EOMONTH(C90,0) -> 42490 | W90: =YEAR(C90) -> 2016
A91: 90 | B91: CA-2016-109806 | C91: 42630 | D91: 9/22/2016 | E91: Standard Class | F91: JS-15685 | G91: Jim Sink | H91: Corporate | I91: United States | J91: Los Angeles | K91: California | L91: 90036 | M91: West | N91: OFF-AR-10004930 | O91: Office Supplies | P91: Art | Q91: Turquoise Lead Holder with Pocket Clip | R91: 20.1 | S91: 3 | T91: 0 | U91: 6.633 | V91: =EOMONTH(C91,0) -> 42643 | W91: =YEAR(C91) -> 2016
A92: 91 | B92: CA-2016-109806 | C92: 42630 | D92: 9/22/2016 | E92: Standard Class | F92: JS-15685 | G92: Jim Sink | H92: Corporate | I92: United States | J92: Los Angeles | K92: California | L92: 90036 | M92: West | N92: TEC-PH-10004093 | O92: Technology | P92: Phones | Q92: Panasonic Kx-TS550 | R92: 73.584 | S92: 2 | T92: 0.2 | U92: 8.2782 | V92: =EOMONTH(C92,0) -> 42643 | W92: =YEAR(C92) -> 2016
A93: 92 | B93: CA-2016-109806 | C93: 42630 | D93: 9/22/2016 | E93: Standard Class | F93: JS-15685 | G93: Jim Sink | H93: Corporate | I93: United States | J93: Los Angeles | K93: California | L93: 90036 | M93: West | N93: OFF-PA-10000304 | O93: Office Supplies | P93: Paper | Q93: Xerox 1995 | R93: 6.48 | S93: 1 | T93: 0 | U93: 3.1104 | V93: =EOMONTH(C93,0) -> 42643 | W93: =YEAR(C93) -> 2016
A94: 93 | B94: CA-2015-149587 | C94: 42035 | D94: 42126 | E94: Second Class | F94: KB-16315 | G94: Karl Braun | H94: Consumer | I94: United States | J94: Minneapolis | K94: Minnesota | L94: 55407 | M94: Central | N94: OFF-PA-10003177 | O94: Office Supplies | P94: Paper | Q94: Xerox 1999 | R94: 12.96 | S94: 2 | T94: 0 | U94: 6.2208 | V94: =EOMONTH(C94,0) -> 42035 | W94: =YEAR(C94) -> 2015
A95: 94 | B95: CA-2015-149587 | C95: 42035 | D95: 42126 | E95: Second Class | F95: KB-16315 | G95: Karl Braun | H95: Consumer | I95: United States | J95: Minneapolis | K95: Minnesota | L95: 55407 | M95: Central | N95: FUR-FU-10003799 | O95: Furniture | P95: Furnishings | Q95: Seth Thomas 13 1/2" Wall Clock | R95: 53.34 | S95: 3 | T95: 0 | U95: 16.5354 | V95: =EOMONTH(C95,0) -> 42035 | W95: =YEAR(C95) -> 2015
A96: 95 | B96: CA-2015-149587 | C96: 42035 | D96: 42126 | E96: Second Class | F96: KB-16315 | G96: Karl Braun | H96: Consumer | I96: United States | J96: Minneapolis | K96: Minnesota | L96: 55407 | M96: Central | N96: OFF-BI-10002852 | O96: Office Supplies | P96: Binders | Q96: Ibico Standard Transparent Covers | R96: 32.96 | S96: 2 | T96: 0 | U96: 16.1504 | V96: =EOMONTH(C96,0) -> 42035 | W96: =YEAR(C96) -> 2015
A97: 96 | B97: US-2017-109484 | C97: 43045 | D97: 43080 | E97: Standard Class | F97: RB-19705 | G97: Roger Barcio | H97: Home Office | I97: United States | J97: Portland | K97: Oregon | L97: 97206 | M97: West | N97: OFF-BI-10004738 | O97: Office Supplies | P97: Binders | Q97: Flexible Leather- Look Classic Collection Ring Binder | R97: 5.682 | S97: 1 | T97: 0.7 | U97: -3.788 | V97: =EOMONTH(C97,0) -> 43069 | W97: =YEAR(C97) -> 2017
A98: 97 | B98: CA-2017-161018 | C98: 43048 | D98: 43050 | E98: Second Class | F98: PN-18775 | G98: Parhena Norris | H98: Home Office | I98: United States | J98: New York City | K98: New York | L98: 10009 | M98: East | N98: FUR-FU-10000629 | O98: Furniture | P98: Furnishings | Q98: 9-3/4 Diameter Round Wall Clock | R98: 96.53 | S98: 7 | T98: 0 | U98: 40.5426 | V98: =EOMONTH(C98,0) -> 43069 | W98: =YEAR(C98) -> 2017
A99: 98 | B99: CA-2017-157833 | C99: 42903 | D99: 6/20/2017 | E99: First Class | F99: KD-16345 | G99: Katherine Ducich | H99: Consumer | I99: United States | J99: San Francisco | K99: California | L99: 94122 | M99: West | N99: OFF-BI-10001721 | O99: Office Supplies | P99: Binders | Q99: Trimflex Flexible Post Binders | R99: 51.312 | S99: 3 | T99: 0.2 | U99: 17.9592 | V99: =EOMONTH(C99,0) -> 42916 | W99: =YEAR(C99) -> 2017
A100: 99 | B100: CA-2016-149223 | C100: 42619 | D100: 42683 | E100: Standard Class | F100: ER-13855 | G100: Elpida Rittenbach | H100: Corporate | I100: United States | J100: Saint Paul | K100: Minnesota | L100: 55106 | M100: Central | N100: OFF-AP-10000358 | O100: Office Supplies | P100: Appliances | Q100: Fellowes Basic Home/Office Series Surge Protectors | R100: 77.88 | S100: 6 | T100: 0 | U100: 22.5852 | V100: =EOMONTH(C100,0) -> 42643 | W100: =YEAR(C100) -> 2016
A101: 100 | B101: CA-2016-158568 | C101: 42611 | D101: 42409 | E101: Standard Class | F101: RB-19465 | G101: Rick Bensley | H101: Home Office | I101: United States | J101: Chicago | K101: Illinois | L101: 60610 | M101: Central | N101: OFF-PA-10003256 | O101: Office Supplies | P101: Paper | Q101: Avery Personal Creations Heavyweight Cards | R101: 64.624 | S101: 7 | T101: 0.2 | U101: 22.6184 | V101: =EOMONTH(C101,0) -> 42613 | W101: =YEAR(C101) -> 2016
A102: 101 | B102: CA-2016-158568 | C102: 42611 | D102: 42409 | E102: Standard Class | F102: RB-19465 | G102: Rick Bensley | H102: Home Office | I102: United States | J102: Chicago | K102: Illinois | L102: 60610 | M102: Central | N102: TEC-AC-10001767 | O102: Technology | P102: Accessories | Q102: SanDisk Ultra 64 GB MicroSDHC Class 10 Memory Card | R102: 95.976 | S102: 3 | T102: 0.2 | U102: -10.7973 | V102: =EOMONTH(C102,0) -> 42613 | W102: =YEAR(C102) -> 2016
A103: 102 | B103: CA-2016-158568 | C103: 42611 | D103: 42409 | E103: Standard Class | F103: RB-19465 | G103: Rick Bensley | H103: Home Office | I103: United States | J103: Chicago | K103: Illinois | L103: 60610 | M103: Central | N103: OFF-BI-10002609 | O103: Office Supplies | P103: Binders | Q103: Avery Hidden Tab Dividers for Binding Systems | R103: 1.788 | S103: 3 | T103: 0.8 | U103: -3.0396 | V103: =EOMONTH(C103,0) -> 42613 | W103: =YEAR(C103) -> 2016
A104: 103 | B104: CA-2016-129903 | C104: 42705 | D104: 42472 | E104: Second Class | F104: GZ-14470 | G104: Gary Zandusky | H104: Consumer | I104: United States | J104: Rochester | K104: Minnesota | L104: 55901 | M104: Central | N104: OFF-PA-10004040 | O104: Office Supplies | P104: Paper | Q104: Universal Premium White Copier/Laser Paper (20Lb. and 87 Bright) | R104: 23.92 | S104: 4 | T104: 0 | U104: 11.7208 | V104: =EOMONTH(C104,0) -> 42735 | W104: =YEAR(C104) -> 2016
A105: 104 | B105: US-2015-156867 | C105: 42321 | D105: 11/17/2015 | E105: Standard Class | F105: LC-16870 | G105: Lena Cacioppo | H105: Consumer | I105: United States | J105: Aurora | K105: Colorado | L105: 80013 | M105: West | N105: TEC-AC-10001552 | O105: Technology | P105: Accessories | Q105: Logitech K350 2.4Ghz Wireless Keyboard | R105: 238.896 | S105: 6 | T105: 0.2 | U105: -26.8758 | V105: =EOMONTH(C105,0) -> 42338 | W105: =YEAR(C105) -> 2015
A106: 105 | B106: US-2015-156867 | C106: 42321 | D106: 11/17/2015 | E106: Standard Class | F106: LC-16870 | G106: Lena Cacioppo | H106: Consumer | I106: United States | J106: Aurora | K106: Colorado | L106: 80013 | M106: West | N106: FUR-FU-10004006 | O106: Furniture | P106: Furnishings | Q106: Deflect-o DuraMat Lighweight, Studded, Beveled Mat for Low Pile Carpeting | R106: 102.36 | S106: 3 | T106: 0.2 | U106: -3.8385 | V106: =EOMONTH(C106,0) -> 42338 | W106: =YEAR(C106) -> 2015
A107: 106 | B107: US-2015-156867 | C107: 42321 | D107: 11/17/2015 | E107: Standard Class | F107: LC-16870 | G107: Lena Cacioppo | H107: Consumer | I107: United States | J107: Aurora | K107: Colorado | L107: 80013 | M107: West | N107: OFF-BI-10002794 | O107: Office Supplies | P107: Binders | Q107: Avery Trapezoid Ring Binder, 3" Capacity, Black, 1040 sheets | R107: 36.882 | S107: 3 | T107: 0.7 | U107: -25.8174 | V107: =EOMONTH(C107,0) -> 42338 | W107: =YEAR(C107) -> 2015
A108: 107 | B108: CA-2017-119004 | C108: 43062 | D108: 11/28/2017 | E108: Standard Class | F108: JM-15250 | G108: Janet Martin | H108: Consumer | I108: United States | J108: Charlotte | K108: North Carolina | L108: 28205 | M108: South | N108: TEC-AC-10003499 | O108: Technology | P108: Accessories | Q108: Memorex Mini Travel Drive 8 GB USB 2.0 Flash Drive | R108: 74.112 | S108: 8 | T108: 0.2 | U108: 17.6016 | V108: =EOMONTH(C108,0) -> 43069 | W108: =YEAR(C108) -> 2017
A109: 108 | B109: CA-2017-119004 | C109: 43062 | D109: 11/28/2017 | E109: Standard Class | F109: JM-15250 | G109: Janet Martin | H109: Consumer | I109: United States | J109: Charlotte | K109: North Carolina | L109: 28205 | M109: South | N109: TEC-PH-10002844 | O109: Technology | P109: Phones | Q109: Speck Products Candyshell Flip Case | R109: 27.992 | S109: 1 | T109: 0.2 | U109: 2.0994 | V109: =EOMONTH(C109,0) -> 43069 | W109: =YEAR(C109) -> 2017
A110: 109 | B110: CA-2017-119004 | C110: 43062 | D110: 11/28/2017 | E110: Standard Class | F110: JM-15250 | G110: Janet Martin | H110: Consumer | I110: United States | J110: Charlotte | K110: North Carolina | L110: 28205 | M110: South | N110: OFF-AR-10000390 | O110: Office Supplies | P110: Art | Q110: Newell Chalk Holder | R110: 3.304 | S110: 1 | T110: 0.2 | U110: 1.0738 | V110: =EOMONTH(C110,0) -> 43069 | W110: =YEAR(C110) -> 2017
A111: 110 | B111: CA-2015-129476 | C111: 42292 | D111: 10/20/2015 | E111: Standard Class | F111: PA-19060 | G111: Pete Armstrong | H111: Home Office | I111: United States | J111: Orland Park | K111: Illinois | L111: 60462 | M111: Central | N111: TEC-AC-10000844 | O111: Technology | P111: Accessories | Q111: Logitech†Gaming G510s - Keyboard | R111: 339.96 | S111: 5 | T111: 0.2 | U111: 67.992 | V111: =EOMONTH(C111,0) -> 42308 | W111: =YEAR(C111) -> 2015
A112: 111 | B112: CA-2017-146780 | C112: 43094 | D112: 12/30/2017 | E112: Standard Class | F112: CV-12805 | G112: Cynthia Voltz | H112: Corporate | I112: United States | J112: New York City | K112: New York | L112: 10035 | M112: East | N112: FUR-FU-10001934 | O112: Furniture | P112: Furnishings | Q112: Magnifier Swing Arm Lamp | R112: 41.96 | S112: 2 | T112: 0 | U112: 10.9096 | V112: =EOMONTH(C112,0) -> 43100 | W112: =YEAR(C112) -> 2017
A113: 112 | B113: CA-2016-128867 | C113: 42677 | D113: 42654 | E113: Standard Class | F113: CL-12565 | G113: Clay Ludtke | H113: Consumer | I113: United States | J113: Urbandale | K113: Iowa | L113: 50322 | M113: Central | N113: OFF-AR-10000380 | O113: Office Supplies | P113: Art | Q113: Hunt PowerHouse Electric Pencil Sharpener, Blue | R113: 75.96 | S113: 2 | T113: 0 | U113: 22.788 | V113: =EOMONTH(C113,0) -> 42704 | W113: =YEAR(C113) -> 2016
A114: 113 | B114: CA-2016-128867 | C114: 42677 | D114: 42654 | E114: Standard Class | F114: CL-12565 | G114: Clay Ludtke | H114: Consumer | I114: United States | J114: Urbandale | K114: Iowa | L114: 50322 | M114: Central | N114: OFF-BI-10003981 | O114: Office Supplies | P114: Binders | Q114: Avery Durable Plastic 1" Binders | R114: 27.24 | S114: 6 | T114: 0 | U114: 13.3476 | V114: =EOMONTH(C114,0) -> 42704 | W114: =YEAR(C114) -> 2016
A115: 114 | B115: CA-2014-115259 | C115: 41876 | D115: 8/27/2014 | E115: Second Class | F115: RC-19960 | G115: Ryan Crowe | H115: Consumer | I115: United States | J115: Columbus | K115: Ohio | L115: 43229 | M115: East | N115: OFF-FA-10000621 | O115: Office Supplies | P115: Fasteners | Q115: OIC Colored Binder Clips, Assorted Sizes | R115: 40.096 | S115: 14 | T115: 0.2 | U115: 14.5348 | V115: =EOMONTH(C115,0) -> 41882 | W115: =YEAR(C115) -> 2014
A116: 115 | B116: CA-2014-115259 | C116: 41876 | D116: 8/27/2014 | E116: Second Class | F116: RC-19960 | G116: Ryan Crowe | H116: Consumer | I116: United States | J116: Columbus | K116: Ohio | L116: 43229 | M116: East | N116: OFF-EN-10002600 | O116: Office Supplies | P116: Envelopes | Q116: Redi-Strip #10 Envelopes, 4 1/8 x 9 1/2 | R116: 4.72 | S116: 2 | T116: 0.2 | U116: 1.652 | V116: =EOMONTH(C116,0) -> 41882 | W116: =YEAR(C116) -> 2014
A117: 116 | B117: CA-2014-115259 | C117: 41876 | D117: 8/27/2014 | E117: Second Class | F117: RC-19960 | G117: Ryan Crowe | H117: Consumer | I117: United States | J117: Columbus | K117: Ohio | L117: 43229 | M117: East | N117: OFF-PA-10004965 | O117: Office Supplies | P117: Paper | Q117: Xerox 1921 | R117: 23.976 | S117: 3 | T117: 0.2 | U117: 7.4925 | V117: =EOMONTH(C117,0) -> 41882 | W117: =YEAR(C117) -> 2014
...

Sheet Dashboard

Sheet sales
A2: {=_xlfn.UNIQUE('[1]Sample - Superstore'!M2:M9995)} -> South | B2: =SUMIFS('Sample - Superstore'!R:R,'Sample - Superstore'!M:M,sales!A2) -> 391721.91 | D2: Row Labels | E2: Sum of Sales | F2: Region | G2: Sales | J2: {=_xlfn.UNIQUE('[1]Sample - Superstore'!V2:V9995)} -> 42704 | K2: =SUMIFS('Sample - Superstore'!R:R,'Sample - Superstore'!V:V,sales!J2) -> 79411.966 | P2: Row Labels | Q2: Sum of Sales | Z2: 2014 | AA2: =SUMIFS('Sample - Superstore'!U:U,'Sample - Superstore'!W:W,sales!Z2) -> 49543.974
A3: West | B3: =SUMIFS('Sample - Superstore'!R:R,'Sample - Superstore'!M:M,sales!A3) -> 725457.82 | D3: Central | E3: 501239.89 | F3: =D3 -> Central | G3: =E3 -> 501239.89 | J3: 42551 | K3: =SUMIFS('Sample - Superstore'!R:R,'Sample - Superstore'!V:V,sales!J3) -> 40344.534 | P3: 41670 | Q3: 14236.895 | R3: =P3 -> 41670 | S3: =Q3 -> 14236.895 | Z3: 2015 | AA3: =SUMIFS('Sample - Superstore'!U:U,'Sample - Superstore'!W:W,sales!Z3) -> 61618.604
A4: Central | B4: =SUMIFS('Sample - Superstore'!R:R,'Sample - Superstore'!M:M,sales!A4) -> 501239.89 | D4: East | E4: 678781.24 | F4: =D4 -> East | G4: =E4 -> 678781.24 | J4: 42308 | K4: =SUMIFS('Sample - Superstore'!R:R,'Sample - Superstore'!V:V,sales!J4) -> 31404.924 | P4: 41698 | Q4: 4519.892 | R4: =P4 -> 41698 | S4: =Q4 -> 4519.892 | Z4: 2016 | AA4: =SUMIFS('Sample - Superstore'!U:U,'Sample - Superstore'!W:W,sales!Z4) -> 81795.174
A5: East | B5: =SUMIFS('Sample - Superstore'!R:R,'Sample - Superstore'!M:M,sales!A5) -> 678781.24 | D5: South | E5: 391721.91 | F5: =D5 -> South | G5: =E5 -> 391721.91 | J5: 41820 | K5: =SUMIFS('Sample - Superstore'!R:R,'Sample - Superstore'!V:V,sales!J5) -> 34595.128 | P5: 41729 | Q5: 55691.009 | R5: =P5 -> 41729 | S5: =Q5 -> 55691.009 | Z5: 2017 | AA5: =SUMIFS('Sample - Superstore'!U:U,'Sample - Superstore'!W:W,sales!Z5) -> 93439.27
D6: West | E6: 725457.82 | F6: =D6 -> West | G6: =E6 -> 725457.82 | J6: 42855 | K6: =SUMIFS('Sample - Superstore'!R:R,'Sample - Superstore'!V:V,sales!J6) -> 36521.536 | P6: 41759 | Q6: 28295.345 | R6: =P6 -> 41759 | S6: =Q6 -> 28295.345
D7: Grand Total | E7: 2297200.9 | F7: =D7 -> Grand Total | G7: =E7 -> 2297200.9 | J7: 42735 | K7: =SUMIFS('Sample - Superstore'!R:R,'Sample - Superstore'!V:V,sales!J7) -> 96999.043 | P7: 41790 | Q7: 23648.287 | R7: =P7 -> 41790 | S7: =Q7 -> 23648.287
J8: 42338 | K8: =SUMIFS('Sample - Superstore'!R:R,'Sample - Superstore'!V:V,sales!J8) -> 75972.564 | P8: 41820 | Q8: 34595.128 | R8: =P8 -> 41820 | S8: =Q8 -> 34595.128 | Z8: {=_xlfn.UNIQUE('Sample - Superstore'!M:M)} -> Region | AA8: profit sum
J9: 41973 | K9: =SUMIFS('Sample - Superstore'!R:R,'Sample - Superstore'!V:V,sales!J9) -> 78628.717 | P9: 41851 | Q9: 33946.393 | R9: =P9 -> 41851 | S9: =Q9 -> 33946.393 | Z9: South | AA9: =SUMIFS('Sample - Superstore'!U:U,'Sample - Superstore'!M:M,sales!Z9) -> 46749.43 | AF9: Row Labels | AG9: Sum of Profit | AI9: Region | AJ9: Total Profit
J10: 41790 | K10: =SUMIFS('Sample - Superstore'!R:R,'Sample - Superstore'!V:V,sales!J10) -> 23648.287 | P10: 41882 | Q10: 27909.468 | R10: =P10 -> 41882 | S10: =Q10 -> 27909.468 | Z10: West | AA10: =SUMIFS('Sample - Superstore'!U:U,'Sample - Superstore'!M:M,sales!Z10) -> 108418.45 | AF10: Central | AG10: 39706.362 | AI10: =AF10 -> Central | AJ10: =AG10 -> 39706.362
J11: 41882 | K11: =SUMIFS('Sample - Superstore'!R:R,'Sample - Superstore'!V:V,sales!J11) -> 27909.468 | P11: 41912 | Q11: 81777.351 | R11: =P11 -> 41912 | S11: =Q11 -> 81777.351 | Z11: Central | AA11: =SUMIFS('Sample - Superstore'!U:U,'Sample - Superstore'!M:M,sales!Z11) -> 39706.362 | AF11: East | AG11: 91522.78 | AI11: =AF11 -> East | AJ11: =AG11 -> 91522.78
J12: 42947 | K12: =SUMIFS('Sample - Superstore'!R:R,'Sample - Superstore'!V:V,sales!J12) -> 45264.416 | P12: 41943 | Q12: 31453.393 | R12: =P12 -> 41943 | S12: =Q12 -> 31453.393 | Z12: East | AA12: =SUMIFS('Sample - Superstore'!U:U,'Sample - Superstore'!M:M,sales!Z12) -> 91522.78 | AF12: South | AG12: 46749.43 | AI12: =AF12 -> South | AJ12: =AG12 -> 46749.43
J13: 42277 | K13: =SUMIFS('Sample - Superstore'!R:R,'Sample - Superstore'!V:V,sales!J13) -> 64595.918 | P13: 41973 | Q13: 78628.717 | R13: =P13 -> 41973 | S13: =Q13 -> 78628.717 | Z13: 0 | AA13: =SUMIFS('Sample - Superstore'!U:U,'Sample - Superstore'!M:M,sales!Z13) -> 0 | AF13: West | AG13: 108418.45 | AI13: =AF13 -> West | AJ13: =AG13 -> 108418.45
J14: 42400 | K14: =SUMIFS('Sample - Superstore'!R:R,'Sample - Superstore'!V:V,sales!J14) -> 18542.491 | P14: 42004 | Q14: 69545.62 | R14: =P14 -> 42004 | S14: =Q14 -> 69545.62 | AF14: Grand Total | AG14: 286397.02
J15: 43039 | K15: =SUMIFS('Sample - Superstore'!R:R,'Sample - Superstore'!V:V,sales!J15) -> 77776.923 | P15: 42035 | Q15: 18174.076 | R15: =P15 -> 42035 | S15: =Q15 -> 18174.076
J16: 42369 | K16: =SUMIFS('Sample - Superstore'!R:R,'Sample - Superstore'!V:V,sales!J16) -> 74919.521 | P16: 42063 | Q16: 11951.411 | R16: =P16 -> 42063 | S16: =Q16 -> 11951.411
J17: 43008 | K17: =SUMIFS('Sample - Superstore'!R:R,'Sample - Superstore'!V:V,sales!J17) -> 87866.652 | P17: 42094 | Q17: 38726.252 | R17: =P17 -> 42094 | S17: =Q17 -> 38726.252
J18: 42582 | K18: =SUMIFS('Sample - Superstore'!R:R,'Sample - Superstore'!V:V,sales!J18) -> 39261.963 | P18: 42124 | Q18: 34195.208 | R18: =P18 -> 42124 | S18: =Q18 -> 34195.208
J19: 42460 | K19: =SUMIFS('Sample - Superstore'!R:R,'Sample - Superstore'!V:V,sales!J19) -> 51715.875 | P19: 42155 | Q19: 30131.686 | R19: =P19 -> 42155 | S19: =Q19 -> 30131.686
J20: 41943 | K20: =SUMIFS('Sample - Superstore'!R:R,'Sample - Superstore'!V:V,sales!J20) -> 31453.393 | P20: 42185 | Q20: 24797.292 | R20: =P20 -> 42185 | S20: =Q20 -> 24797.292
J21: 42124 | K21: =SUMIFS('Sample - Superstore'!R:R,'Sample - Superstore'!V:V,sales!J21) -> 34195.208 | P21: 42216 | Q21: 28765.325 | R21: =P21 -> 42216 | S21: =Q21 -> 28765.325
J22: 42004 | K22: =SUMIFS('Sample - Superstore'!R:R,'Sample - Superstore'!V:V,sales!J22) -> 69545.62 | P22: 42247 | Q22: 36898.332 | R22: =P22 -> 42247 | S22: =Q22 -> 36898.332
J23: 42643 | K23: =SUMIFS('Sample - Superstore'!R:R,'Sample - Superstore'!V:V,sales!J23) -> 73410.025 | P23: 42277 | Q23: 64595.918 | R23: =P23 -> 42277 | S23: =Q23 -> 64595.918
J24: 43100 | K24: =SUMIFS('Sample - Superstore'!R:R,'Sample - Superstore'!V:V,sales!J24) -> 83829.319 | P24: 42308 | Q24: 31404.924 | R24: =P24 -> 42308 | S24: =Q24 -> 31404.924
A25: Total Sales | C25: Sum of Profit | E25: Sum of Quantity | G25: =COUNTA(Table1[Order ID]) -> 9994 | J25: 43069 | K25: =SUMIFS('Sample - Superstore'!R:R,'Sample - Superstore'!V:V,sales!J25) -> 118447.83 | P25: 42338 | Q25: 75972.564 | R25: =P25 -> 42338 | S25: =Q25 -> 75972.564
A26: 2297200.9 | C26: 286397.02 | E26: 37873 | G26: =A26/G25 -> 229.858 | J26: 42886 | K26: =SUMIFS('Sample - Superstore'!R:R,'Sample - Superstore'!V:V,sales!J26) -> 44261.11 | N26: quantity range | O26: frequency | P26: 42369 | Q26: 74919.521 | R26: =P26 -> 42369 | S26: =Q26 -> 74919.521
J27: 42490 | K27: =SUMIFS('Sample - Superstore'!R:R,'Sample - Superstore'!V:V,sales!J27) -> 38750.039 | N27: 1-2 | O27: =COUNTIFS('Sample - Superstore'!R:R,">=1",'Sample - Superstore'!R:R,"<=2") -> 72 | P27: 42400 | Q27: 18542.491 | R27: =P27 -> 42400 | S27: =Q27 -> 18542.491
A28: Total Sales | C28: Total Profit | E28: Total Quantity | G28: Average Order Value | J28: 42035 | K28: =SUMIFS('Sample - Superstore'!R:R,'Sample - Superstore'!V:V,sales!J28) -> 18174.076 | N28: 3-5 | O28: =COUNTIFS('Sample - Superstore'!R:R,">=3",'Sample - Superstore'!R:R,"<=5") -> 297 | P28: 42429 | Q28: 22978.815 | R28: =P28 -> 42429 | S28: =Q28 -> 22978.815
A29: =TEXT(A26,"$#,###,.0k") -> $2,297.2k | C29: =TEXT(C26,"$#,###,.0k") -> $286.4k | D29: =TEXT(D26,"#,###") | E29: =TEXT(E26,"#,###") -> 37,873 | F29: =TEXT(F26,"#,###") | G29: =TEXT(G26,"#,###") -> 230 | J29: 42916 | K29: =SUMIFS('Sample - Superstore'!R:R,'Sample - Superstore'!V:V,sales!J29) -> 52981.726 | N29: 6-10 | O29: =COUNTIFS('Sample - Superstore'!R:R,">=6",'Sample - Superstore'!R:R,"<=10") -> 673 | P29: 42460 | Q29: 51715.875 | R29: =P29 -> 42460 | S29: =Q29 -> 51715.875
J30: 42613 | K30: =SUMIFS('Sample - Superstore'!R:R,'Sample - Superstore'!V:V,sales!J30) -> 31115.374 | N30: 11+ | O30: =COUNTIFS('Sample - Superstore'!R:R,">=11") -> 8459 | P30: 42490 | Q30: 38750.039 | R30: =P30 -> 42490 | S30: =Q30 -> 38750.039
J31: 42094 | K31: =SUMIFS('Sample - Superstore'!R:R,'Sample - Superstore'!V:V,sales!J31) -> 38726.252 | P31: 42521 | Q31: 56987.728 | R31: =P31 -> 42521 | S31: =Q31 -> 56987.728
J32: 41912 | K32: =SUMIFS('Sample - Superstore'!R:R,'Sample - Superstore'!V:V,sales!J32) -> 81777.351 | P32: 42551 | Q32: 40344.534 | R32: =P32 -> 42551 | S32: =Q32 -> 40344.534
J33: 42794 | K33: =SUMIFS('Sample - Superstore'!R:R,'Sample - Superstore'!V:V,sales!J33) -> 20301.133 | P33: 42582 | Q33: 39261.963 | R33: =P33 -> 42582 | S33: =Q33 -> 39261.963
A34: Region | B34: (All) | J34: 42674 | K34: =SUMIFS('Sample - Superstore'!R:R,'Sample - Superstore'!V:V,sales!J34) -> 59687.745 | P34: 42613 | Q34: 31115.374 | R34: =P34 -> 42613 | S34: =Q34 -> 31115.374
A35: Category | B35: (All) | J35: 42155 | K35: =SUMIFS('Sample - Superstore'!R:R,'Sample - Superstore'!V:V,sales!J35) -> 30131.686 | P35: 42643 | Q35: 73410.025 | R35: =P35 -> 42643 | S35: =Q35 -> 73410.025
J36: 41729 | K36: =SUMIFS('Sample - Superstore'!R:R,'Sample - Superstore'!V:V,sales!J36) -> 55691.009 | P36: 42674 | Q36: 59687.745 | R36: =P36 -> 42674 | S36: =Q36 -> 59687.745 | Z36: =N38 -> 0 | AA36: =O38 -> 66.900292
J37: 42521 | K37: =SUMIFS('Sample - Superstore'!R:R,'Sample - Superstore'!V:V,sales!J37) -> 56987.728 | N37: Row Labels | O37: Average of Profit | P37: 42704 | Q37: 79411.966 | R37: =P37 -> 42704 | S37: =Q37 -> 79411.966 | Z37: =N39 -> 0.1 | AA37: =O39 -> 96.055074
J38: 42063 | K38: =SUMIFS('Sample - Superstore'!R:R,'Sample - Superstore'!V:V,sales!J38) -> 11951.411 | N38: 0 | O38: 66.900292 | P38: 42735 | Q38: 96999.043 | R38: =P38 -> 42735 | S38: =Q38 -> 96999.043 | Z38: =N40 -> 0.15 | AA38: =O40 -> 27.288298
J39: 42247 | K39: =SUMIFS('Sample - Superstore'!R:R,'Sample - Superstore'!V:V,sales!J39) -> 36898.332 | N39: 0.1 | O39: 96.055074 | P39: 42766 | Q39: 43971.374 | R39: =P39 -> 42766 | S39: =Q39 -> 43971.374 | Z39: =N41 -> 0.2 | AA39: =O41 -> 24.702572
J40: 42216 | K40: =SUMIFS('Sample - Superstore'!R:R,'Sample - Superstore'!V:V,sales!J40) -> 28765.325 | N40: 0.15 | O40: 27.288298 | P40: 42794 | Q40: 20301.133 | R40: =P40 -> 42794 | S40: =Q40 -> 20301.133 | Z40: =N42 -> 0.3 | AA40: =O42 -> -45.679636
J41: 41851 | K41: =SUMIFS('Sample - Superstore'!R:R,'Sample - Superstore'!V:V,sales!J41) -> 33946.393 | N41: 0.2 | O41: 24.702572 | P41: 42825 | Q41: 58872.353 | R41: =P41 -> 42825 | S41: =Q41 -> 58872.353 | Z41: =N43 -> 0.32 | AA41: =O43 -> -88.560656
J42: 42185 | K42: =SUMIFS('Sample - Superstore'!R:R,'Sample - Superstore'!V:V,sales!J42) -> 24797.292 | N42: 0.3 | O42: -45.679636 | P42: 42855 | Q42: 36521.536 | R42: =P42 -> 42855 | S42: =Q42 -> 36521.536 | Z42: =N44 -> 0.4 | AA42: =O44 -> -111.92743
J43: 41759 | K43: =SUMIFS('Sample - Superstore'!R:R,'Sample - Superstore'!V:V,sales!J43) -> 28295.345 | N43: 0.32 | O43: -88.560656 | P43: 42886 | Q43: 44261.11 | R43: =P43 -> 42886 | S43: =Q43 -> 44261.11 | Z43: =N45 -> 0.45 | AA43: =O45 -> -226.64646
J44: 42825 | K44: =SUMIFS('Sample - Superstore'!R:R,'Sample - Superstore'!V:V,sales!J44) -> 58872.353 | N44: 0.4 | O44: -111.92743 | P44: 42916 | Q44: 52981.726 | R44: =P44 -> 42916 | S44: =Q44 -> 52981.726 | Z44: =N46 -> 0.5 | AA44: =O46 -> -310.70346
J45: 42978 | K45: =SUMIFS('Sample - Superstore'!R:R,'Sample - Superstore'!V:V,sales!J45) -> 63120.888 | N45: 0.45 | O45: -226.64646 | P45: 42947 | Q45: 45264.416 | R45: =P45 -> 42947 | S45: =Q45 -> 45264.416 | Z45: =N47 -> 0.6 | AA45: =O47 -> -43.077212
J46: 42766 | K46: =SUMIFS('Sample - Superstore'!R:R,'Sample - Superstore'!V:V,sales!J46) -> 43971.374 | N46: 0.5 | O46: -310.70346 | P46: 42978 | Q46: 63120.888 | R46: =P46 -> 42978 | S46: =Q46 -> 63120.888 | Z46: =N48 -> 0.7 | AA46: =O48 -> -95.87406
J47: 41698 | K47: =SUMIFS('Sample - Superstore'!R:R,'Sample - Superstore'!V:V,sales!J47) -> 4519.892 | N47: 0.6 | O47: -43.077212 | P47: 43008 | Q47: 87866.652 | R47: =P47 -> 43008 | S47: =Q47 -> 87866.652 | Z47: =N49 -> 0.8 | AA47: =O49 -> -101.7968
J48: 41670 | K48: =SUMIFS('Sample - Superstore'!R:R,'Sample - Superstore'!V:V,sales!J48) -> 14236.895 | N48: 0.7 | O48: -95.87406 | P48: 43039 | Q48: 77776.923 | R48: =P48 -> 43039 | S48: =Q48 -> 77776.923
J49: 42429 | K49: =SUMIFS('Sample - Superstore'!R:R,'Sample - Superstore'!V:V,sales!J49) -> 22978.815 | N49: 0.8 | O49: -101.7968 | P49: 43069 | Q49: 118447.83 | R49: =P49 -> 43069 | S49: =Q49 -> 118447.83
N50: Grand Total | O50: 28.656896 | P50: 43100 | Q50: 83829.319 | R50: =P50 -> 43100 | S50: =Q50 -> 83829.319
P51: Grand Total | Q51: 2297200.9 | R51: =P51 -> Grand Total | S51: =Q51 -> 2297200.9

Sheet year wise sales
L4: region
L5: {=_xlfn.UNIQUE('Sample - Superstore'!M2:M9995)} -> South
L6: West
B7: region | C7: West | L7: Central
L8: East
B10: Order Year | C10: Furniture | D10: Office Supplies | E10: Technology
B11: {=_xlfn.UNIQUE('Sample - Superstore'!W2:W9995)} -> 2016 | C11: =SUMIFS('Sample - Superstore'!$R$2:$R$9995,'Sample - Superstore'!$W$2:$W$9995,'year wise sales'!$B11,'Sample - Superstore'!$O$2:$O$9995,'year wise sales'!C$10,'Sample - Superstore'!$M$2:$M$9995,'year wise sales'!$C$7) -> 73819.64 | D11: =SUMIFS('Sample - Superstore'!$R$2:$R$9995,'Sample - Superstore'!$W$2:$W$9995,'year wise sales'!$B11,'Sample - Superstore'!$O$2:$O$9995,'year wise sales'!D$10,'Sample - Superstore'!$M$2:$M$9995,'year wise sales'!$C$7) -> 47679.357 | E11: =SUMIFS('Sample - Superstore'!$R$2:$R$9995,'Sample - Superstore'!$W$2:$W$9995,'year wise sales'!$B11,'Sample - Superstore'!$O$2:$O$9995,'year wise sales'!E$10,'Sample - Superstore'!$M$2:$M$9995,'year wise sales'!$C$7) -> 65981.179
B12: 2015 | C12: =SUMIFS('Sample - Superstore'!$R$2:$R$9995,'Sample - Superstore'!$W$2:$W$9995,'year wise sales'!$B12,'Sample - Superstore'!$O$2:$O$9995,'year wise sales'!C$10,'Sample - Superstore'!$M$2:$M$9995,'year wise sales'!$C$7) -> 57004.943 | D12: =SUMIFS('Sample - Superstore'!$R$2:$R$9995,'Sample - Superstore'!$W$2:$W$9995,'year wise sales'!$B12,'Sample - Superstore'!$O$2:$O$9995,'year wise sales'!D$10,'Sample - Superstore'!$M$2:$M$9995,'year wise sales'!$C$7) -> 37863.532 | E12: =SUMIFS('Sample - Superstore'!$R$2:$R$9995,'Sample - Superstore'!$W$2:$W$9995,'year wise sales'!$B12,'Sample - Superstore'!$O$2:$O$9995,'year wise sales'!E$10,'Sample - Superstore'!$M$2:$M$9995,'year wise sales'!$C$7) -> 45097.774
B13: 2014 | C13: =SUMIFS('Sample - Superstore'!$R$2:$R$9995,'Sample - Superstore'!$W$2:$W$9995,'year wise sales'!$B13,'Sample - Superstore'!$O$2:$O$9995,'year wise sales'!C$10,'Sample - Superstore'!$M$2:$M$9995,'year wise sales'!$C$7) -> 50082.448 | D13: =SUMIFS('Sample - Superstore'!$R$2:$R$9995,'Sample - Superstore'!$W$2:$W$9995,'year wise sales'!$B13,'Sample - Superstore'!$O$2:$O$9995,'year wise sales'!D$10,'Sample - Superstore'!$M$2:$M$9995,'year wise sales'!$C$7) -> 52846.854 | E13: =SUMIFS('Sample - Superstore'!$R$2:$R$9995,'Sample - Superstore'!$W$2:$W$9995,'year wise sales'!$B13,'Sample - Superstore'!$O$2:$O$9995,'year wise sales'!E$10,'Sample - Superstore'!$M$2:$M$9995,'year wise sales'!$C$7) -> 44953.731
B14: 2017 | C14: =SUMIFS('Sample - Superstore'!$R$2:$R$9995,'Sample - Superstore'!$W$2:$W$9995,'year wise sales'!$B14,'Sample - Superstore'!$O$2:$O$9995,'year wise sales'!C$10,'Sample - Superstore'!$M$2:$M$9995,'year wise sales'!$C$7) -> 71705.711 | D14: =SUMIFS('Sample - Superstore'!$R$2:$R$9995,'Sample - Superstore'!$W$2:$W$9995,'year wise sales'!$B14,'Sample - Superstore'!$O$2:$O$9995,'year wise sales'!D$10,'Sample - Superstore'!$M$2:$M$9995,'year wise sales'!$C$7) -> 82463.506 | E14: =SUMIFS('Sample - Superstore'!$R$2:$R$9995,'Sample - Superstore'!$W$2:$W$9995,'year wise sales'!$B14,'Sample - Superstore'!$O$2:$O$9995,'year wise sales'!E$10,'Sample - Superstore'!$M$2:$M$9995,'year wise sales'!$C$7) -> 95959.148
B27: Sum of Sales | C27: Column Labels
B28: Row Labels | C28: Furniture | D28: Office Supplies | E28: Technology | F28: Grand Total | H28: Order Year | I28: Furniture | J28: Office Supplies | K28: Technology
B29: 2014 | C29: 157192.85 | D29: 151776.41 | E29: 175278.23 | F29: 484247.5 | H29: =B29 -> 2014 | I29: =C29 -> 157192.85 | J29: =D29 -> 151776.41 | K29: =E29 -> 175278.23
B30: 2015 | C30: 170518.24 | D30: 137233.46 | E30: 162780.81 | F30: 470532.51 | H30: =B30 -> 2015 | I30: =C30 -> 170518.24 | J30: =D30 -> 137233.46 | K30: =E30 -> 162780.81
B31: 2016 | C31: 198901.44 | D31: 183939.98 | E31: 226364.18 | F31: 609205.6 | H31: =B31 -> 2016 | I31: =C31 -> 198901.44 | J31: =D31 -> 183939.98 | K31: =E31 -> 226364.18
B32: 2017 | C32: 215471.24 | D32: 246097.18 | E32: 271646.84 | F32: 733215.26 | H32: =B32 -> 2017 | I32: =C32 -> 215471.24 | J32: =D32 -> 246097.18 | K32: =E32 -> 271646.84
B33: Grand Total | C33: 742083.77 | D33: 719047.03 | E33: 836070.06 | F33: 2297200.9

Sheet Detail1
A1: Details for Average of Sales2 - order month: 3/31/2014, order year: 2014 (+)
A3: Row ID | B3: Order ID | C3: Order Date | D3: Ship Date | E3: Ship Mode | F3: Customer ID | G3: Customer Name | H3: Segment | I3: Country | J3: City | K3: State | L3: Postal Code | M3: Region | N3: Product ID | O3: Category | P3: Sub-Category | Q3: Product Name | R3: Sales | S3: Quantity | T3: Discount | U3: Profit | V3: order month | W3: order year
A4: 9947 | B4: CA-2014-111157 | C4: 41700 | D4: 41793 | E4: Standard Class | F4: NH-18610 | G4: Nicole Hansen | H4: Corporate | I4: United States | J4: Philadelphia | K4: Pennsylvania | L4: 19120 | M4: East | N4: TEC-AC-10004353 | O4: Technology | P4: Accessories | Q4: Hypercom P1300 Pinpad | R4: 151.2 | S4: 3 | T4: 0.2 | U4: 32.13 | V4: 41729 | W4: 2014
A5: 9946 | B5: CA-2014-111157 | C5: 41700 | D5: 41793 | E5: Standard Class | F5: NH-18610 | G5: Nicole Hansen | H5: Corporate | I5: United States | J5: Philadelphia | K5: Pennsylvania | L5: 19120 | M5: East | N5: OFF-PA-10000327 | O5: Office Supplies | P5: Paper | Q5: Xerox 1971 | R5: 3.424 | S5: 1 | T5: 0.2 | U5: 1.07 | V5: 41729 | W5: 2014
A6: 9900 | B6: US-2014-117380 | C6: 41726 | D6: 41702 | E6: Standard Class | F6: MP-18175 | G6: Mike Pelletier | H6: Home Office | I6: United States | J6: Springfield | K6: Ohio | L6: 45503 | M6: East | N6: FUR-TA-10000198 | O6: Furniture | P6: Tables | Q6: Chromcraft Bull-Nose Wood Oval Conference Tables & Bases | R6: 330.588 | S6: 1 | T6: 0.4 | U6: -143.2548 | V6: 41729 | W6: 2014
A7: 9660 | B7: CA-2014-100860 | C7: 41724 | D7: 3/30/2014 | E7: Second Class | F7: CS-12505 | G7: Cindy Stewart | H7: Consumer | I7: United States | J7: Pomona | K7: California | L7: 91767 | M7: West | N7: OFF-LA-10001982 | O7: Office Supplies | P7: Labels | Q7: Smead Alpha-Z Color-Coded Name Labels First Letter Starter Set | R7: 18.75 | S7: 5 | T7: 0 | U7: 9 | V7: 41729 | W7: 2014
A8: 9644 | B8: CA-2014-104563 | C8: 41705 | D8: 41976 | E8: Standard Class | F8: CM-12715 | G8: Craig Molinari | H8: Corporate | I8: United States | J8: Seattle | K8: Washington | L8: 98103 | M8: West | N8: FUR-CH-10004495 | O8: Furniture | P8: Chairs | Q8: Global Leather and Oak Executive Chair, Black | R8: 481.568 | S8: 2 | T8: 0.2 | U8: 54.1764 | V8: 41729 | W8: 2014
A9: 9643 | B9: CA-2014-104563 | C9: 41705 | D9: 41976 | E9: Standard Class | F9: CM-12715 | G9: Craig Molinari | H9: Corporate | I9: United States | J9: Seattle | K9: Washington | L9: 98103 | M9: West | N9: FUR-CH-10002780 | O9: Furniture | P9: Chairs | Q9: Office Star - Task Chair with Contemporary Loop Arms | R9: 436.704 | S9: 6 | T9: 0.2 | U9: 21.8352 | V9: 41729 | W9: 2014
A10: 9642 | B10: CA-2014-104563 | C10: 41705 | D10: 41976 | E10: Standard Class | F10: CM-12715 | G10: Craig Molinari | H10: Corporate | I10: United States | J10: Seattle | K10: Washington | L10: 98103 | M10: West | N10: OFF-ST-10000934 | O10: Office Supplies | P10: Storage | Q10: Contico 72"H Heavy-Duty Storage System | R10: 204.9 | S10: 5 | T10: 0 | U10: 0 | V10: 41729 | W10: 2014
A11: 9641 | B11: CA-2014-104563 | C11: 41705 | D11: 41976 | E11: Standard Class | F11: CM-12715 | G11: Craig Molinari | H11: Corporate | I11: United States | J11: Seattle | K11: Washington | L11: 98103 | M11: West | N11: OFF-AR-10000390 | O11: Office Supplies | P11: Art | Q11: Newell Chalk Holder | R11: 20.65 | S11: 5 | T11: 0 | U11: 9.499 | V11: 41729 | W11: 2014
A12: 9568 | B12: CA-2014-130428 | C12: 41729 | D12: 3/31/2014 | E12: Same Day | F12: TG-21640 | G12: Trudy Glocke | H12: Consumer | I12: United States | J12: Tampa | K12: Florida | L12: 33614 | M12: South | N12: OFF-AR-10004027 | O12: Office Supplies | P12: Art | Q12: Binney & Smith inkTank Erasable Desk Highlighter, Chisel Tip, Yellow, 12/Box | R12: 4.032 | S12: 2 | T12: 0.2 | U12: 1.0584 | V12: 41729 | W12: 2014
A13: 9567 | B13: CA-2014-130428 | C13: 41729 | D13: 3/31/2014 | E13: Same Day | F13: TG-21640 | G13: Trudy Glocke | H13: Consumer | I13: United States | J13: Tampa | K13: Florida | L13: 33614 | M13: South | N13: OFF-BI-10001636 | O13: Office Supplies | P13: Binders | Q13: Ibico Plastic and Wire Spiral Binding Combs | R13: 12.645 | S13: 5 | T13: 0.7 | U13: -10.116 | V13: 41729 | W13: 2014
A14: 9566 | B14: CA-2014-130428 | C14: 41729 | D14: 3/31/2014 | E14: Same Day | F14: TG-21640 | G14: Trudy Glocke | H14: Consumer | I14: United States | J14: Tampa | K14: Florida | L14: 33614 | M14: South | N14: FUR-CH-10002965 | O14: Furniture | P14: Chairs | Q14: Global Leather Highback Executive Chair with Pneumatic Height Adjustment, Black | R14: 1125.488 | S14: 7 | T14: 0.2 | U14: 98.4802 | V14: 41729 | W14: 2014
A15: 9515 | B15: CA-2014-100293 | C15: 41712 | D15: 3/18/2014 | E15: Standard Class | F15: NF-18475 | G15: Neil Franzˆsisch | H15: Home Office | I15: United States | J15: Jacksonville | K15: Florida | L15: 32216 | M15: South | N15: OFF-PA-10000176 | O15: Office Supplies | P15: Paper | Q15: Xerox 1887 | R15: 91.056 | S15: 6 | T15: 0.2 | U15: 31.8696 | V15: 41729 | W15: 2014
A16: 9407 | B16: CA-2014-152618 | C16: 41712 | D16: 3/17/2014 | E16: First Class | F16: RB-19465 | G16: Rick Bensley | H16: Home Office | I16: United States | J16: Chicago | K16: Illinois | L16: 60653 | M16: Central | N16: OFF-PA-10001215 | O16: Office Supplies | P16: Paper | Q16: Xerox 1963 | R16: 8.448 | S16: 2 | T16: 0.2 | U16: 2.64 | V16: 41729 | W16: 2014
A17: 9406 | B17: CA-2014-152618 | C17: 41712 | D17: 3/17/2014 | E17: First Class | F17: RB-19465 | G17: Rick Bensley | H17: Home Office | I17: United States | J17: Chicago | K17: Illinois | L17: 60653 | M17: Central | N17: TEC-MA-10003626 | O17: Technology | P17: Machines | Q17: Hewlett-Packard Deskjet 6540 Color Inkjet Printer | R17: 574.91 | S17: 2 | T17: 0.3 | U17: 156.047 | V17: 41729 | W17: 2014
A18: 9310 | B18: CA-2014-128237 | C18: 41723 | D18: 3/30/2014 | E18: Standard Class | F18: CA-12265 | G18: Christina Anderson | H18: Consumer | I18: United States | J18: San Francisco | K18: California | L18: 94110 | M18: West | N18: OFF-AR-10000034 | O18: Office Supplies | P18: Art | Q18: BIC Brite Liner Grip Highlighters, Assorted, 5/Pack | R18: 25.44 | S18: 6 | T18: 0 | U18: 9.9216 | V18: 41729 | W18: 2014
A19: 9309 | B19: CA-2014-128237 | C19: 41723 | D19: 3/30/2014 | E19: Standard Class | F19: CA-12265 | G19: Christina Anderson | H19: Consumer | I19: United States | J19: San Francisco | K19: California | L19: 94110 | M19: West | N19: TEC-AC-10002558 | O19: Technology | P19: Accessories | Q19: Imation†Swivel†Flash Drive†USB†flash drive†- 8 GB | R19: 45.48 | S19: 4 | T19: 0 | U19: 15.918 | V19: 41729 | W19: 2014
A20: 9308 | B20: CA-2014-128237 | C20: 41723 | D20: 3/30/2014 | E20: Standard Class | F20: CA-12265 | G20: Christina Anderson | H20: Consumer | I20: United States | J20: San Francisco | K20: California | L20: 94110 | M20: West | N20: OFF-AR-10003338 | O20: Office Supplies | P20: Art | Q20: Eberhard Faber 3 1/2" Golf Pencils | R20: 14.88 | S20: 2 | T20: 0 | U20: 3.72 | V20: 41729 | W20: 2014
A21: 9307 | B21: CA-2014-128237 | C21: 41723 | D21: 3/30/2014 | E21: Standard Class | F21: CA-12265 | G21: Christina Anderson | H21: Consumer | I21: United States | J21: San Francisco | K21: California | L21: 94110 | M21: West | N21: OFF-AR-10003829 | O21: Office Supplies | P21: Art | Q21: Newell 35 | R21: 6.56 | S21: 2 | T21: 0 | U21: 1.9024 | V21: 41729 | W21: 2014
A22: 9054 | B22: CA-2014-141838 | C22: 41724 | D22: 3/31/2014 | E22: Second Class | F22: DK-12835 | G22: Damala Kotsonis | H22: Corporate | I22: United States | J22: San Francisco | K22: California | L22: 94122 | M22: West | N22: TEC-PH-10004100 | O22: Technology | P22: Phones | Q22: Griffin GC17055 Auxiliary Audio Cable | R22: 28.784 | S22: 2 | T22: 0.2 | U22: 2.8784 | V22: 41729 | W22: 2014
A23: 9053 | B23: CA-2014-141838 | C23: 41724 | D23: 3/31/2014 | E23: Second Class | F23: DK-12835 | G23: Damala Kotsonis | H23: Corporate | I23: United States | J23: San Francisco | K23: California | L23: 94122 | M23: West | N23: OFF-BI-10003291 | O23: Office Supplies | P23: Binders | Q23: Wilson Jones Leather-Like Binders with DublLock Round Rings | R23: 27.936 | S23: 4 | T23: 0.2 | U23: 9.4284 | V23: 41729 | W23: 2014
A24: 9052 | B24: CA-2014-141838 | C24: 41724 | D24: 3/31/2014 | E24: Second Class | F24: DK-12835 | G24: Damala Kotsonis | H24: Corporate | I24: United States | J24: San Francisco | K24: California | L24: 94122 | M24: West | N24: OFF-AR-10004272 | O24: Office Supplies | P24: Art | Q24: Newell 308 | R24: 3.36 | S24: 2 | T24: 0 | U24: 0.84 | V24: 41729 | W24: 2014
A25: 8712 | B25: CA-2014-105648 | C25: 41701 | D25: 41823 | E25: Standard Class | F25: EJ-14155 | G25: Eva Jacobs | H25: Consumer | I25: United States | J25: San Diego | K25: California | L25: 92037 | M25: West | N25: FUR-TA-10002958 | O25: Furniture | P25: Tables | Q25: Bevis Oval Conference Table, Walnut | R25: 626.352 | S25: 3 | T25: 0.2 | U25: -23.4882 | V25: 41729 | W25: 2014
A26: 8501 | B26: CA-2014-169061 | C26: 41703 | D26: 41854 | E26: Second Class | F26: AB-10150 | G26: Aimee Bixby | H26: Consumer | I26: United States | J26: Yonkers | K26: New York | L26: 10701 | M26: East | N26: OFF-PA-10001878 | O26: Office Supplies | P26: Paper | Q26: Xerox 1891 | R26: 97.82 | S26: 2 | T26: 0 | U26: 45.9754 | V26: 41729 | W26: 2014
A27: 8500 | B27: CA-2014-169061 | C27: 41703 | D27: 41854 | E27: Second Class | F27: AB-10150 | G27: Aimee Bixby | H27: Consumer | I27: United States | J27: Yonkers | K27: New York | L27: 10701 | M27: East | N27: OFF-BI-10001617 | O27: Office Supplies | P27: Binders | Q27: GBC Wire Binding Combs | R27: 49.632 | S27: 6 | T27: 0.2 | U27: 16.7508 | V27: 41729 | W27: 2014
A28: 8499 | B28: CA-2014-169061 | C28: 41703 | D28: 41854 | E28: Second Class | F28: AB-10150 | G28: Aimee Bixby | H28: Consumer | I28: United States | J28: Yonkers | K28: New York | L28: 10701 | M28: East | N28: OFF-SU-10000381 | O28: Office Supplies | P28: Supplies | Q28: Acme Forged Steel Scissors with Black Enamel Handles | R28: 18.62 | S28: 2 | T28: 0 | U28: 5.3998 | V28: 41729 | W28: 2014
A29: 8498 | B29: CA-2014-169061 | C29: 41703 | D29: 41854 | E29: Second Class | F29: AB-10150 | G29: Aimee Bixby | H29: Consumer | I29: United States | J29: Yonkers | K29: New York | L29: 10701 | M29: East | N29: TEC-AC-10002001 | O29: Technology | P29: Accessories | Q29: Logitech Wireless Gaming Headset G930 | R29: 479.97 | S29: 3 | T29: 0 | U29: 177.5889 | V29: 41729 | W29: 2014
A30: 8497 | B30: CA-2014-169061 | C30: 41703 | D30: 41854 | E30: Second Class | F30: AB-10150 | G30: Aimee Bixby | H30: Consumer | I30: United States | J30: Yonkers | K30: New York | L30: 10701 | M30: East | N30: OFF-AR-10000588 | O30: Office Supplies | P30: Art | Q30: Newell 345 | R30: 59.52 | S30: 3 | T30: 0 | U30: 15.4752 | V30: 41729 | W30: 2014
A31: 8464 | B31: CA-2014-100881 | C31: 41726 | D31: 41643 | E31: Standard Class | F31: DR-12940 | G31: Daniel Raglin | H31: Home Office | I31: United States | J31: Albuquerque | K31: New Mexico | L31: 87105 | M31: West | N31: TEC-PH-10003273 | O31: Technology | P31: Phones | Q31: AT&T TR1909W | R31: 302.376 | S31: 3 | T31: 0.2 | U31: 22.6782 | V31: 41729 | W31: 2014
A32: 8431 | B32: US-2014-113124 | C32: 41728 | D32: 41763 | E32: Standard Class | F32: NC-18340 | G32: Nat Carroll | H32: Consumer | I32: United States | J32: Apple Valley | K32: Minnesota | L32: 55124 | M32: Central | N32: OFF-ST-10001511 | O32: Office Supplies | P32: Storage | Q32: Space Solutions Commercial Steel Shelving | R32: 129.3 | S32: 2 | T32: 0 | U32: 6.465 | V32: 41729 | W32: 2014
A33: 8346 | B33: US-2014-155544 | C33: 41719 | D33: 3/25/2014 | E33: Standard Class | F33: GM-14440 | G33: Gary McGarr | H33: Consumer | I33: United States | J33: Knoxville | K33: Tennessee | L33: 37918 | M33: South | N33: FUR-CH-10000422 | O33: Furniture | P33: Chairs | Q33: Global Highback Leather Tilter in Burgundy | R33: 218.376 | S33: 3 | T33: 0.2 | U33: -10.9188 | V33: 41729 | W33: 2014
A34: 8345 | B34: US-2014-155544 | C34: 41719 | D34: 3/25/2014 | E34: Standard Class | F34: GM-14440 | G34: Gary McGarr | H34: Consumer | I34: United States | J34: Knoxville | K34: Tennessee | L34: 37918 | M34: South | N34: FUR-FU-10001473 | O34: Furniture | P34: Furnishings | Q34: DAX Wood Document Frame | R34: 32.952 | S34: 3 | T34: 0.2 | U34: 6.5904 | V34: 41729 | W34: 2014
A35: 8344 | B35: US-2014-155544 | C35: 41719 | D35: 3/25/2014 | E35: Standard Class | F35: GM-14440 | G35: Gary McGarr | H35: Consumer | I35: United States | J35: Knoxville | K35: Tennessee | L35: 37918 | M35: South | N35: OFF-LA-10004544 | O35: Office Supplies | P35: Labels | Q35: Avery 505 | R35: 59.2 | S35: 5 | T35: 0.2 | U35: 22.2 | V35: 41729 | W35: 2014
A36: 8311 | B36: CA-2014-168312 | C36: 41699 | D36: 41823 | E36: Standard Class | F36: GW-14605 | G36: Giulietta Weimer | H36: Consumer | I36: United States | J36: Houston | K36: Texas | L36: 77036 | M36: Central | N36: FUR-TA-10001866 | O36: Furniture | P36: Tables | Q36: Bevis Round Conference Room Tables and Bases | R36: 376.509 | S36: 3 | T36: 0.3 | U36: -43.0296 | V36: 41729 | W36: 2014
A37: 8310 | B37: CA-2014-168312 | C37: 41699 | D37: 41823 | E37: Standard Class | F37: GW-14605 | G37: Giulietta Weimer | H37: Consumer | I37: United States | J37: Houston | K37: Texas | L37: 77036 | M37: Central | N37: OFF-ST-10003692 | O37: Office Supplies | P37: Storage | Q37: Recycled Steel Personal File for Hanging File Folders | R37: 137.352 | S37: 3 | T37: 0.2 | U37: 8.5845 | V37: 41729 | W37: 2014
A38: 8300 | B38: US-2014-103338 | C38: 41709 | D38: 3/15/2014 | E38: Standard Class | F38: RB-19435 | G38: Richard Bierner | H38: Consumer | I38: United States | J38: Roseville | K38: California | L38: 95661 | M38: West | N38: OFF-AR-10001770 | O38: Office Supplies | P38: Art | Q38: Economy #2 Pencils | R38: 7.98 | S38: 3 | T38: 0 | U38: 2.0748 | V38: 41729 | W38: 2014
A39: 8011 | B39: CA-2014-127859 | C39: 41715 | D39: 3/20/2014 | E39: Second Class | F39: QJ-19255 | G39: Quincy Jones | H39: Corporate | I39: United States | J39: Philadelphia | K39: Pennsylvania | L39: 19134 | M39: East | N39: OFF-PA-10003641 | O39: Office Supplies | P39: Paper | Q39: Xerox 1909 | R39: 126.624 | S39: 6 | T39: 0.2 | U39: 41.1528 | V39: 41729 | W39: 2014
A40: 7951 | B40: CA-2014-131009 | C40: 41699 | D40: 41762 | E40: Standard Class | F40: SC-20380 | G40: Shahid Collister | H40: Consumer | I40: United States | J40: El Paso | K40: Texas | L40: 79907 | M40: Central | N40: OFF-ST-10001469 | O40: Office Supplies | P40: Storage | Q40: Fellowes Bankers Box Recycled Super Stor/Drawer | R40: 129.552 | S40: 3 | T40: 0.2 | U40: -22.6716 | V40: 41729 | W40: 2014
A41: 7950 | B41: CA-2014-131009 | C41: 41699 | D41: 41762 | E41: Standard Class | F41: SC-20380 | G41: Shahid Collister | H41: Consumer | I41: United States | J41: El Paso | K41: Texas | L41: 79907 | M41: Central | N41: FUR-FU-10001095 | O41: Furniture | P41: Furnishings | Q41: DAX Black Cherry Wood-Tone Poster Frame | R41: 63.552 | S41: 6 | T41: 0.6 | U41: -34.9536 | V41: 41729 | W41: 2014
A42: 7949 | B42: CA-2014-131009 | C42: 41699 | D42: 41762 | E42: Standard Class | F42: SC-20380 | G42: Shahid Collister | H42: Consumer | I42: United States | J42: El Paso | K42: Texas | L42: 79907 | M42: Central | N42: FUR-CH-10001270 | O42: Furniture | P42: Chairs | Q42: Harbour Creations Steel Folding Chair | R42: 362.25 | S42: 6 | T42: 0.3 | U42: 0 | V42: 41729 | W42: 2014
A43: 7948 | B43: CA-2014-131009 | C43: 41699 | D43: 41762 | E43: Standard Class | F43: SC-20380 | G43: Shahid Collister | H43: Consumer | I43: United States | J43: El Paso | K43: Texas | L43: 79907 | M43: Central | N43: OFF-FA-10004395 | O43: Office Supplies | P43: Fasteners | Q43: Plymouth Boxed Rubber Bands by Plymouth | R43: 18.84 | S43: 5 | T43: 0.2 | U43: -3.5325 | V43: 41729 | W43: 2014
A44: 7841 | B44: US-2014-137869 | C44: 41726 | D44: 41674 | E44: Standard Class | F44: CV-12295 | G44: Christina VanderZanden | H44: Consumer | I44: United States | J44: Des Moines | K44: Iowa | L44: 50315 | M44: Central | N44: FUR-TA-10003954 | O44: Furniture | P44: Tables | Q44: Hon 94000 Series Round Tables | R44: 1184.72 | S44: 4 | T44: 0 | U44: 106.6248 | V44: 41729 | W44: 2014
A45: 7840 | B45: US-2014-137869 | C45: 41726 | D45: 41674 | E45: Standard Class | F45: CV-12295 | G45: Christina VanderZanden | H45: Consumer | I45: United States | J45: Des Moines | K45: Iowa | L45: 50315 | M45: Central | N45: OFF-EN-10001509 | O45: Office Supplies | P45: Envelopes | Q45: Poly String Tie Envelopes | R45: 6.12 | S45: 3 | T45: 0 | U45: 2.8764 | V45: 41729 | W45: 2014
A46: 7802 | B46: CA-2014-143637 | C46: 41722 | D46: 3/29/2014 | E46: Second Class | F46: MS-17710 | G46: Maurice Satty | H46: Consumer | I46: United States | J46: Fresno | K46: California | L46: 93727 | M46: West | N46: FUR-FU-10002813 | O46: Furniture | P46: Furnishings | Q46: DAX Contemporary Wood Frame with Silver Metal Mat, Desktop, 11 x 14 Size | R46: 40.48 | S46: 2 | T46: 0 | U46: 14.5728 | V46: 41729 | W46: 2014
A47: 7632 | B47: CA-2014-162089 | C47: 41728 | D47: 41643 | E47: First Class | F47: MP-17470 | G47: Mark Packer | H47: Home Office | I47: United States | J47: Brownsville | K47: Texas | L47: 78521 | M47: Central | N47: FUR-CH-10002304 | O47: Furniture | P47: Chairs | Q47: Global Stack Chair without Arms, Black | R47: 127.302 | S47: 7 | T47: 0.3 | U47: -9.093 | V47: 41729 | W47: 2014
A48: 7631 | B48: CA-2014-162089 | C48: 41728 | D48: 41643 | E48: First Class | F48: MP-17470 | G48: Mark Packer | H48: Home Office | I48: United States | J48: Brownsville | K48: Texas | L48: 78521 | M48: Central | N48: TEC-PH-10001819 | O48: Technology | P48: Phones | Q48: Innergie mMini Combo Duo USB Travel Charging Kit | R48: 251.944 | S48: 7 | T48: 0.2 | U48: 88.1804 | V48: 41729 | W48: 2014
A49: 7630 | B49: CA-2014-162089 | C49: 41728 | D49: 41643 | E49: First Class | F49: MP-17470 | G49: Mark Packer | H49: Home Office | I49: United States | J49: Brownsville | K49: Texas | L49: 78521 | M49: Central | N49: OFF-EN-10002230 | O49: Office Supplies | P49: Envelopes | Q49: Airmail Envelopes | R49: 335.72 | S49: 5 | T49: 0.2 | U49: 113.3055 | V49: 41729 | W49: 2014
A50: 7588 | B50: CA-2014-163223 | C50: 41719 | D50: 3/25/2014 | E50: Standard Class | F50: KH-16690 | G50: Kristen Hastings | H50: Corporate | I50: United States | J50: Springfield | K50: Virginia | L50: 22153 | M50: South | N50: OFF-BI-10001597 | O50: Office Supplies | P50: Binders | Q50: Wilson Jones Ledger-Size, Piano-Hinge Binder, 2", Blue | R50: 122.94 | S50: 3 | T50: 0 | U50: 59.0112 | V50: 41729 | W50: 2014
A51: 7587 | B51: CA-2014-163223 | C51: 41719 | D51: 3/25/2014 | E51: Standard Class | F51: KH-16690 | G51: Kristen Hastings | H51: Corporate | I51: United States | J51: Springfield | K51: Virginia | L51: 22153 | M51: South | N51: OFF-AR-10001573 | O51: Office Supplies | P51: Art | Q51: American Pencil | R51: 9.32 | S51: 4 | T51: 0 | U51: 2.7028 | V51: 41729 | W51: 2014
A52: 7586 | B52: CA-2014-163223 | C52: 41719 | D52: 3/25/2014 | E52: Standard Class | F52: KH-16690 | G52: Kristen Hastings | H52: Corporate | I52: United States | J52: Springfield | K52: Virginia | L52: 22153 | M52: South | N52: OFF-PA-10000675 | O52: Office Supplies | P52: Paper | Q52: Xerox 1919 | R52: 122.97 | S52: 3 | T52: 0 | U52: 60.2553 | V52: 41729 | W52: 2014
A53: 7585 | B53: CA-2014-163223 | C53: 41719 | D53: 3/25/2014 | E53: Standard Class | F53: KH-16690 | G53: Kristen Hastings | H53: Corporate | I53: United States | J53: Springfield | K53: Virginia | L53: 22153 | M53: South | N53: OFF-LA-10004409 | O53: Office Supplies | P53: Labels | Q53: Avery 492 | R53: 14.4 | S53: 5 | T53: 0 | U53: 6.624 | V53: 41729 | W53: 2014
A54: 7584 | B54: CA-2014-163223 | C54: 41719 | D54: 3/25/2014 | E54: Standard Class | F54: KH-16690 | G54: Kristen Hastings | H54: Corporate | I54: United States | J54: Springfield | K54: Virginia | L54: 22153 | M54: South | N54: TEC-PH-10000730 | O54: Technology | P54: Phones | Q54: Samsung Galaxy S4 Active | R54: 3499.93 | S54: 7 | T54: 0 | U54: 909.9818 | V54: 41729 | W54: 2014
A55: 7432 | B55: US-2014-164763 | C55: 41715 | D55: 3/21/2014 | E55: Standard Class | F55: MH-17440 | G55: Mark Haberlin | H55: Corporate | I55: United States | J55: Jackson | K55: Mississippi | L55: 39212 | M55: South | N55: OFF-AP-10003971 | O55: Office Supplies | P55: Appliances | Q55: Belkin 6 Outlet Metallic Surge Strip | R55: 32.67 | S55: 3 | T55: 0 | U55: 8.4942 | V55: 41729 | W55: 2014
A56: 7431 | B56: US-2014-164763 | C56: 41715 | D56: 3/21/2014 | E56: Standard Class | F56: MH-17440 | G56: Mark Haberlin | H56: Corporate | I56: United States | J56: Jackson | K56: Mississippi | L56: 39212 | M56: South | N56: OFF-PA-10003063 | O56: Office Supplies | P56: Paper | Q56: EcoTones Memo Sheets | R56: 16 | S56: 4 | T56: 0 | U56: 7.68 | V56: 41729 | W56: 2014
A57: 7430 | B57: US-2014-164763 | C57: 41715 | D57: 3/21/2014 | E57: Standard Class | F57: MH-17440 | G57: Mark Haberlin | H57: Corporate | I57: United States | J57: Jackson | K57: Mississippi | L57: 39212 | M57: South | N57: OFF-PA-10003349 | O57: Office Supplies | P57: Paper | Q57: Xerox 1957 | R57: 12.96 | S57: 2 | T57: 0 | U57: 6.3504 | V57: 41729 | W57: 2014
A58: 7429 | B58: US-2014-164763 | C58: 41715 | D58: 3/21/2014 | E58: Standard Class | F58: MH-17440 | G58: Mark Haberlin | H58: Corporate | I58: United States | J58: Jackson | K58: Mississippi | L58: 39212 | M58: South | N58: OFF-BI-10000309 | O58: Office Supplies | P58: Binders | Q58: GBC Twin Loop Wire Binding Elements, 9/16" Spine, Black | R58: 30.44 | S58: 2 | T58: 0 | U58: 14.9156 | V58: 41729 | W58: 2014
A59: 7428 | B59: US-2014-164763 | C59: 41715 | D59: 3/21/2014 | E59: Standard Class | F59: MH-17440 | G59: Mark Haberlin | H59: Corporate | I59: United States | J59: Jackson | K59: Mississippi | L59: 39212 | M59: South | N59: OFF-BI-10000605 | O59: Office Supplies | P59: Binders | Q59: Acco Pressboard Covers with Storage Hooks, 9 1/2" x 11", Executive Red | R59: 11.43 | S59: 3 | T59: 0 | U59: 5.3721 | V59: 41729 | W59: 2014
A60: 7349 | B60: CA-2014-130421 | C60: 41701 | D60: 41823 | E60: Standard Class | F60: SC-20020 | G60: Sam Craven | H60: Consumer | I60: United States | J60: Houston | K60: Texas | L60: 77095 | M60: Central | N60: OFF-AP-10002534 | O60: Office Supplies | P60: Appliances | Q60: 3.6 Cubic Foot Counter Height Office Refrigerator | R60: 176.772 | S60: 3 | T60: 0.8 | U60: -459.6072 | V60: 41729 | W60: 2014
A61: 7330 | B61: US-2014-131275 | C61: 41716 | D61: 3/24/2014 | E61: Standard Class | F61: SC-20050 | G61: Sample Company A | H61: Home Office | I61: United States | J61: Burbank | K61: California | L61: 91505 | M61: West | N61: OFF-ST-10000078 | O61: Office Supplies | P61: Storage | Q61: Tennsco 6- and 18-Compartment Lockers | R61: 1856.19 | S61: 7 | T61: 0 | U61: 334.1142 | V61: 41729 | W61: 2014
A62: 7329 | B62: US-2014-131275 | C62: 41716 | D62: 3/24/2014 | E62: Standard Class | F62: SC-20050 | G62: Sample Company A | H62: Home Office | I62: United States | J62: Burbank | K62: California | L62: 91505 | M62: West | N62: TEC-MA-10001148 | O62: Technology | P62: Machines | Q62: Swingline SM12-08 MicroCut Jam Free Shredder | R62: 1279.968 | S62: 4 | T62: 0.2 | U62: 415.9896 | V62: 41729 | W62: 2014
A63: 7328 | B63: US-2014-131275 | C63: 41716 | D63: 3/24/2014 | E63: Standard Class | F63: SC-20050 | G63: Sample Company A | H63: Home Office | I63: United States | J63: Burbank | K63: California | L63: 91505 | M63: West | N63: FUR-FU-10004597 | O63: Furniture | P63: Furnishings | Q63: Eldon Cleatmat Chair Mats for Medium Pile Carpets | R63: 111 | S63: 2 | T63: 0 | U63: 14.43 | V63: 41729 | W63: 2014
A64: 7306 | B64: CA-2014-137274 | C64: 41727 | D64: 41674 | E64: Standard Class | F64: MG-18145 | G64: Mike Gockenbach | H64: Consumer | I64: United States | J64: Plano | K64: Texas | L64: 75023 | M64: Central | N64: FUR-TA-10001889 | O64: Furniture | P64: Tables | Q64: Bush Advantage Collection Racetrack Conference Table | R64: 890.841 | S64: 3 | T64: 0.3 | U64: -152.7156 | V64: 41729 | W64: 2014
A65: 7249 | B65: US-2014-127978 | C65: 41701 | D65: 41854 | E65: Standard Class | F65: JS-15595 | G65: Jill Stevenson | H65: Corporate | I65: United States | J65: Columbus | K65: Ohio | L65: 43229 | M65: East | N65: OFF-ST-10002486 | O65: Office Supplies | P65: Storage | Q65: Eldon Shelf Savers Cubes and Bins | R65: 44.672 | S65: 8 | T65: 0.2 | U65: -10.0512 | V65: 41729 | W65: 2014
A66: 7248 | B66: US-2014-127978 | C66: 41701 | D66: 41854 | E66: Standard Class | F66: JS-15595 | G66: Jill Stevenson | H66: Corporate | I66: United States | J66: Columbus | K66: Ohio | L66: 43229 | M66: East | N66: FUR-BO-10001972 | O66: Furniture | P66: Bookcases | Q66: O'Sullivan 4-Shelf Bookcase in Odessa Pine | R66: 302.45 | S66: 5 | T66: 0.5 | U66: -199.617 | V66: 41729 | W66: 2014
A67: 7247 | B67: US-2014-127978 | C67: 41701 | D67: 41854 | E67: Standard Class | F67: JS-15595 | G67: Jill Stevenson | H67: Corporate | I67: United States | J67: Columbus | K67: Ohio | L67: 43229 | M67: East | N67: OFF-LA-10000305 | O67: Office Supplies | P67: Labels | Q67: Avery 495 | R67: 15.12 | S67: 3 | T67: 0.2 | U67: 4.914 | V67: 41729 | W67: 2014
A68: 7018 | B68: CA-2014-114790 | C68: 41709 | D68: 3/13/2014 | E68: Second Class | F68: FM-14215 | G68: Filia McAdams | H68: Corporate | I68: United States | J68: Richmond | K68: Kentucky | L68: 40475 | M68: South | N68: OFF-PA-10000213 | O68: Office Supplies | P68: Paper | Q68: Xerox 198 | R68: 14.94 | S68: 3 | T68: 0 | U68: 7.0218 | V68: 41729 | W68: 2014
A69: 7017 | B69: CA-2014-114790 | C69: 41709 | D69: 3/13/2014 | E69: Second Class | F69: FM-14215 | G69: Filia McAdams | H69: Corporate | I69: United States | J69: Richmond | K69: Kentucky | L69: 40475 | M69: South | N69: TEC-PH-10000984 | O69: Technology | P69: Phones | Q69: Panasonic KX-TG9471B | R69: 587.97 | S69: 3 | T69: 0 | U69: 164.6316 | V69: 41729 | W69: 2014
A70: 7016 | B70: CA-2014-114790 | C70: 41709 | D70: 3/13/2014 | E70: Second Class | F70: FM-14215 | G70: Filia McAdams | H70: Corporate | I70: United States | J70: Richmond | K70: Kentucky | L70: 40475 | M70: South | N70: TEC-AC-10000710 | O70: Technology | P70: Accessories | Q70: Maxell DVD-RAM Discs | R70: 32.96 | S70: 2 | T70: 0 | U70: 14.1728 | V70: 41729 | W70: 2014
A71: 7015 | B71: CA-2014-114790 | C71: 41709 | D71: 3/13/2014 | E71: Second Class | F71: FM-14215 | G71: Filia McAdams | H71: Corporate | I71: United States | J71: Richmond | K71: Kentucky | L71: 40475 | M71: South | N71: OFF-AP-10002578 | O71: Office Supplies | P71: Appliances | Q71: Fellowes Premier Superior Surge Suppressor, 10-Outlet, With Phone and Remote | R71: 146.76 | S71: 3 | T71: 0 | U71: 38.1576 | V71: 41729 | W71: 2014
A72: 6591 | B72: CA-2014-164749 | C72: 41721 | D72: 3/26/2014 | E72: First Class | F72: BG-11740 | G72: Bruce Geld | H72: Consumer | I72: United States | J72: Delray Beach | K72: Florida | L72: 33445 | M72: South | N72: OFF-LA-10004484 | O72: Office Supplies | P72: Labels | Q72: Avery 476 | R72: 9.912 | S72: 3 | T72: 0.2 | U72: 3.2214 | V72: 41729 | W72: 2014
A73: 6549 | B73: CA-2014-113880 | C73: 41699 | D73: 41762 | E73: Standard Class | F73: VF-21715 | G73: Vicky Freymann | H73: Home Office | I73: United States | J73: Elmhurst | K73: Illinois | L73: 60126 | M73: Central | N73: OFF-PA-10003036 | O73: Office Supplies | P73: Paper | Q73: Black Print Carbonless 8 1/2" x 8 1/4" Rapid Memo Book | R73: 17.472 | S73: 3 | T73: 0.2 | U73: 5.6784 | V73: 41729 | W73: 2014
A74: 6548 | B74: CA-2014-113880 | C74: 41699 | D74: 41762 | E74: Standard Class | F74: VF-21715 | G74: Vicky Freymann | H74: Home Office | I74: United States | J74: Elmhurst | K74: Illinois | L74: 60126 | M74: Central | N74: FUR-CH-10000863 | O74: Furniture | P74: Chairs | Q74: Novimex Swivel Fabric Task Chair | R74: 634.116 | S74: 6 | T74: 0.3 | U74: -172.1172 | V74: 41729 | W74: 2014
A75: 6167 | B75: CA-2014-103989 | C75: 41717 | D75: 3/21/2014 | E75: First Class | F75: MC-17605 | G75: Matt Connell | H75: Corporate | I75: United States | J75: Lakeland | K75: Florida | L75: 33801 | M75: South | N75: TEC-AC-10002647 | O75: Technology | P75: Accessories | Q75: Logitech†Wireless Boombox Speaker - portable - wireless, wired | R75: 170.24 | S75: 2 | T75: 0.2 | U75: 53.2 | V75: 41729 | W75: 2014
A76: 6166 | B76: CA-2014-103989 | C76: 41717 | D76: 3/21/2014 | E76: First Class | F76: MC-17605 | G76: Matt Connell | H76: Corporate | I76: United States | J76: Lakeland | K76: Florida | L76: 33801 | M76: South | N76: FUR-FU-10002508 | O76: Furniture | P76: Furnishings | Q76: Document Clip Frames | R76: 20.016 | S76: 3 | T76: 0.2 | U76: 5.5044 | V76: 41729 | W76: 2014
A77: 6165 | B77: CA-2014-103989 | C77: 41717 | D77: 3/21/2014 | E77: First Class | F77: MC-17605 | G77: Matt Connell | H77: Corporate | I77: United States | J77: Lakeland | K77: Florida | L77: 33801 | M77: South | N77: FUR-FU-10003981 | O77: Furniture | P77: Furnishings | Q77: Eldon Wave Desk Accessories | R77: 4.992 | S77: 3 | T77: 0.2 | U77: 1.3728 | V77: 41729 | W77: 2014
A78: 6164 | B78: CA-2014-103989 | C78: 41717 | D78: 3/21/2014 | E78: First Class | F78: MC-17605 | G78: Matt Connell | H78: Corporate | I78: United States | J78: Lakeland | K78: Florida | L78: 33801 | M78: South | N78: OFF-BI-10001196 | O78: Office Supplies | P78: Binders | Q78: Avery Flip-Chart Easel Binder, Black | R78: 33.57 | S78: 5 | T78: 0.7 | U78: -25.737 | V78: 41729 | W78: 2014
A79: 6163 | B79: CA-2014-103989 | C79: 41717 | D79: 3/21/2014 | E79: First Class | F79: MC-17605 | G79: Matt Connell | H79: Corporate | I79: United States | J79: Lakeland | K79: Florida | L79: 33801 | M79: South | N79: OFF-ST-10000918 | O79: Office Supplies | P79: Storage | Q79: Crate-A-Files | R79: 26.16 | S79: 3 | T79: 0.2 | U79: 1.962 | V79: 41729 | W79: 2014
A80: 6162 | B80: CA-2014-103989 | C80: 41717 | D80: 3/21/2014 | E80: First Class | F80: MC-17605 | G80: Matt Connell | H80: Corporate | I80: United States | J80: Lakeland | K80: Florida | L80: 33801 | M80: South | N80: OFF-LA-10000443 | O80: Office Supplies | P80: Labels | Q80: Avery 501 | R80: 11.808 | S80: 4 | T80: 0.2 | U80: 3.9852 | V80: 41729 | W80: 2014
A81: 6161 | B81: CA-2014-103989 | C81: 41717 | D81: 3/21/2014 | E81: First Class | F81: MC-17605 | G81: Matt Connell | H81: Corporate | I81: United States | J81: Lakeland | K81: Florida | L81: 33801 | M81: South | N81: TEC-PH-10004667 | O81: Technology | P81: Phones | Q81: Cisco 8x8 Inc. 6753i IP Business Phone System | R81: 323.976 | S81: 3 | T81: 0.2 | U81: 28.3479 | V81: 41729 | W81: 2014
A82: 6152 | B82: CA-2014-111871 | C82: 41716 | D82: 3/21/2014 | E82: Second Class | F82: EK-13795 | G82: Eileen Kiefer | H82: Home Office | I82: United States | J82: San Francisco | K82: California | L82: 94110 | M82: West | N82: FUR-BO-10004218 | O82: Furniture | P82: Bookcases | Q82: Bush Heritage Pine Collection 5-Shelf Bookcase, Albany Pine Finish, *Special Order | R82: 1198.33 | S82: 10 | T82: 0.15 | U82: 70.49 | V82: 41729 | W82: 2014
A83: 6139 | B83: CA-2014-131247 | C83: 41728 | D83: 41733 | E83: Standard Class | F83: GA-14725 | G83: Guy Armstrong | H83: Consumer | I83: United States | J83: San Francisco | K83: California | L83: 94110 | M83: West | N83: FUR-BO-10001337 | O83: Furniture | P83: Bookcases | Q83: O'Sullivan Living Dimensions 2-Shelf Bookcases | R83: 205.666 | S83: 2 | T83: 0.15 | U83: -12.098 | V83: 41729 | W83: 2014
A84: 6059 | B84: CA-2014-107524 | C84: 41700 | D84: 41854 | E84: Standard Class | F84: KN-16705 | G84: Kristina Nunn | H84: Home Office | I84: United States | J84: New York City | K84: New York | L84: 10009 | M84: East | N84: OFF-PA-10000587 | O84: Office Supplies | P84: Paper | Q84: Array Parchment Paper, Assorted Colors | R84: 36.4 | S84: 5 | T84: 0 | U84: 17.472 | V84: 41729 | W84: 2014
A85: 6058 | B85: CA-2014-107524 | C85: 41700 | D85: 41854 | E85: Standard Class | F85: KN-16705 | G85: Kristina Nunn | H85: Home Office | I85: United States | J85: New York City | K85: New York | L85: 10009 | M85: East | N85: OFF-EN-10001990 | O85: Office Supplies | P85: Envelopes | Q85: Staple envelope | R85: 11.36 | S85: 2 | T85: 0 | U85: 5.3392 | V85: 41729 | W85: 2014
A86: 5954 | B86: US-2014-105151 | C86: 41728 | D86: 3/31/2014 | E86: First Class | F86: SG-20890 | G86: Susan Gilcrest | H86: Corporate | I86: United States | J86: New York City | K86: New York | L86: 10009 | M86: East | N86: OFF-AR-10001231 | O86: Office Supplies | P86: Art | Q86: Sanford EarthWrite Recycled Pencils, Medium Soft, #2 | R86: 10.5 | S86: 5 | T86: 0 | U86: 2.94 | V86: 41729 | W86: 2014
A87: 5714 | B87: US-2014-143707 | C87: 41699 | D87: 41762 | E87: Standard Class | F87: HR-14770 | G87: Hallie Redmond | H87: Home Office | I87: United States | J87: New York City | K87: New York | L87: 10035 | M87: East | N87: TEC-PH-10003655 | O87: Technology | P87: Phones | Q87: Sannysis Cute Owl Design Soft Skin Case Cover for Samsung Galaxy S4 | R87: 5.94 | S87: 3 | T87: 0 | U87: 1.6038 | V87: 41729 | W87: 2014
A88: 5480 | B88: CA-2014-101770 | C88: 41729 | D88: 41733 | E88: Standard Class | F88: KB-16240 | G88: Karen Bern | H88: Corporate | I88: United States | J88: Miami | K88: Florida | L88: 33180 | M88: South | N88: OFF-BI-10001097 | O88: Office Supplies | P88: Binders | Q88: Avery Hole Reinforcements | R88: 1.869 | S88: 1 | T88: 0.7 | U88: -1.3083 | V88: 41729 | W88: 2014
A89: 5461 | B89: US-2014-107405 | C89: 41719 | D89: 3/25/2014 | E89: Standard Class | F89: TS-21205 | G89: Thomas Seio | H89: Corporate | I89: United States | J89: Asheville | K89: North Carolina | L89: 28806 | M89: South | N89: OFF-ST-10002301 | O89: Office Supplies | P89: Storage | Q89: Tennsco Commercial Shelving | R89: 16.272 | S89: 1 | T89: 0.2 | U89: -3.8646 | V89: 41729 | W89: 2014
A90: 5285 | B90: CA-2014-133424 | C90: 41728 | D90: 41733 | E90: Standard Class | F90: Dl-13600 | G90: Dorris liebe | H90: Corporate | I90: United States | J90: Seattle | K90: Washington | L90: 98105 | M90: West | N90: OFF-LA-10002312 | O90: Office Supplies | P90: Labels | Q90: Avery 490 | R90: 44.4 | S90: 3 | T90: 0 | U90: 22.2 | V90: 41729 | W90: 2014
A91: 5284 | B91: CA-2014-133424 | C91: 41728 | D91: 41733 | E91: Standard Class | F91: Dl-13600 | G91: Dorris liebe | H91: Corporate | I91: United States | J91: Seattle | K91: Washington | L91: 98105 | M91: West | N91: OFF-ST-10002957 | O91: Office Supplies | P91: Storage | Q91: Sterilite Show Offs Storage Containers | R91: 15.84 | S91: 3 | T91: 0 | U91: 0 | V91: 41729 | W91: 2014
A92: 5254 | B92: US-2014-131982 | C92: 41705 | D92: 41946 | E92: Second Class | F92: NP-18685 | G92: Nora Pelletier | H92: Home Office | I92: United States | J92: Des Moines | K92: Washington | L92: 98198 | M92: West | N92: OFF-BI-10004224 | O92: Office Supplies | P92: Binders | Q92: Catalog Binders with Expanding Posts | R92: 107.648 | S92: 2 | T92: 0.2 | U92: 33.64 | V92: 41729 | W92: 2014
A93: 5103 | B93: CA-2014-158442 | C93: 41715 | D93: 3/17/2014 | E93: Same Day | F93: AZ-10750 | G93: Annie Zypern | H93: Consumer | I93: United States | J93: Dallas | K93: Texas | L93: 75217 | M93: Central | N93: OFF-PA-10002365 | O93: Office Supplies | P93: Paper | Q93: Xerox 1967 | R93: 15.552 | S93: 3 | T93: 0.2 | U93: 5.4432 | V93: 41729 | W93: 2014
A94: 5102 | B94: CA-2014-158442 | C94: 41715 | D94: 3/17/2014 | E94: Same Day | F94: AZ-10750 | G94: Annie Zypern | H94: Consumer | I94: United States | J94: Dallas | K94: Texas | L94: 75217 | M94: Central | N94: OFF-PA-10002195 | O94: Office Supplies | P94: Paper | Q94: Xerox 1966 | R94: 5.184 | S94: 1 | T94: 0.2 | U94: 1.8792 | V94: 41729 | W94: 2014
A95: 5101 | B95: CA-2014-158442 | C95: 41715 | D95: 3/17/2014 | E95: Same Day | F95: AZ-10750 | G95: Annie Zypern | H95: Consumer | I95: United States | J95: Dallas | K95: Texas | L95: 75217 | M95: Central | N95: OFF-AR-10003732 | O95: Office Supplies | P95: Art | Q95: Newell 333 | R95: 4.448 | S95: 2 | T95: 0.2 | U95: 0.3336 | V95: 41729 | W95: 2014
A96: 5050 | B96: US-2014-104759 | C96: 41729 | D96: 41733 | E96: Standard Class | F96: DD-13570 | G96: Dorothy Dickinson | H96: Consumer | I96: United States | J96: Chicago | K96: Illinois | L96: 60610 | M96: Central | N96: TEC-AC-10004901 | O96: Technology | P96: Accessories | Q96: Kensington SlimBlade Notebook Wireless Mouse with Nano Receiver | R96: 79.984 | S96: 2 | T96: 0.2 | U96: 13.9972 | V96: 41729 | W96: 2014
A97: 5049 | B97: US-2014-104759 | C97: 41729 | D97: 41733 | E97: Standard Class | F97: DD-13570 | G97: Dorothy Dickinson | H97: Consumer | I97: United States | J97: Chicago | K97: Illinois | L97: 60610 | M97: Central | N97: OFF-BI-10002071 | O97: Office Supplies | P97: Binders | Q97: Fellowes Black Plastic Comb Bindings | R97: 8.134 | S97: 7 | T97: 0.8 | U97: -13.8278 | V97: 41729 | W97: 2014
A98: 4964 | B98: CA-2014-156587 | C98: 41705 | D98: 41854 | E98: First Class | F98: AB-10015 | G98: Aaron Bergman | H98: Consumer | I98: United States | J98: Seattle | K98: Washington | L98: 98103 | M98: West | N98: OFF-ST-10002344 | O98: Office Supplies | P98: Storage | Q98: Carina 42"Hx23 3/4"W Media Storage Unit | R98: 242.94 | S98: 3 | T98: 0 | U98: 4.8588 | V98: 41729 | W98: 2014
A99: 4963 | B99: CA-2014-156587 | C99: 41705 | D99: 41854 | E99: First Class | F99: AB-10015 | G99: Aaron Bergman | H99: Consumer | I99: United States | J99: Seattle | K99: Washington | L99: 98103 | M99: West | N99: OFF-AR-10001427 | O99: Office Supplies | P99: Art | Q99: Newell 330 | R99: 17.94 | S99: 3 | T99: 0 | U99: 4.6644 | V99: 41729 | W99: 2014
A100: 4962 | B100: CA-2014-156587 | C100: 41705 | D100: 41854 | E100: First Class | F100: AB-10015 | G100: Aaron Bergman | H100: Consumer | I100: United States | J100: Seattle | K100: Washington | L100: 98103 | M100: West | N100: FUR-CH-10004477 | O100: Furniture | P100: Chairs | Q100: Global Push Button Manager's Chair, Indigo | R100: 48.712 | S100: 1 | T100: 0.2 | U100: 5.4801 | V100: 41729 | W100: 2014
A101: 4712 | B101: CA-2014-112403 | C101: 41729 | D101: 3/31/2014 | E101: Same Day | F101: JO-15280 | G101: Jas O'Carroll | H101: Consumer | I101: United States | J101: Philadelphia | K101: Pennsylvania | L101: 19120 | M101: East | N101: OFF-BI-10003529 | O101: Office Supplies | P101: Binders | Q101: Avery Round Ring Poly Binders | R101: 0.852 | S101: 1 | T101: 0.7 | U101: -0.5964 | V101: 41729 | W101: 2014
...

Sheet Sheet6
A1: order year | B1: (All)
A3: Row Labels | B3: Sum of Sales | C3: Average of Sales2
A4: 41670 | B4: 14236.895 | C4: 180.21386
A5: 41698 | B5: 4519.892 | C5: 98.258522
A6: 41729 | B6: 55691.009 | C6: 354.7198 | E6: sum of sales(first 6 months) | F6: =SUM(OFFSET(B3,COUNT(B:B),0,6)) -> 2297200.9
A7: 41759 | B7: 28295.345 | C7: 209.59515 | E7: Average sales (first 6 months) | F7: =AVERAGE(OFFSET(C3,COUNT(C:C),0,6)) -> 229.858
A8: 41790 | B8: 23648.287 | C8: 193.83842 | E8: sum of sales(last 6 months) | F8: =SUM(OFFSET(B3,COUNT(B:B),0,-6)) -> 2728242.5
A9: 41820 | B9: 34595.128 | C9: 256.2602 | E9: Average sales (last 6 months) | F9: =AVERAGE(OFFSET(C3,COUNT(C:C),0,-6)) -> 235.22256
A10: 41851 | B10: 33946.393 | C10: 237.38736
A11: 41882 | B11: 27909.468 | C11: 182.41483
A12: 41912 | B12: 81777.351 | C12: 305.13937
A13: 41943 | B13: 31453.393 | C13: 197.82008
A14: 41973 | B14: 78628.717 | C14: 247.26012
A15: 42004 | B15: 69545.62 | C15: 250.1641
A16: 42035 | B16: 18174.076 | C16: 313.34613
A17: 42063 | B17: 11951.411 | C17: 186.7408
A18: 42094 | B18: 38726.252 | C18: 280.62501
A19: 42124 | B19: 34195.208 | C19: 213.72005
A20: 42155 | B20: 30131.686 | C20: 206.38141
A21: 42185 | B21: 24797.292 | C21: 179.69052
... A51: 43100 | B51: 83829.319 | C51: 181.44874
A52: Grand Total | B52: 2297200.9 | C52: 229.858

Sheet sales and profit by segment
O3: Row Labels | P3: Sum of Profit | R3: year | S3: profit
O4: 2014 | P4: 49543.974 | R4: =O4 -> 2014 | S4: =P4 -> 49543.974
O5: 2015 | P5: 61618.604 | R5: =O5 -> 2015 | S5: =P5 -> 61618.604
O6: 2016 | P6: 81795.174 | R6: =O6 -> 2016 | S6: =P6 -> 81795.174
B7: segment | C7: sales | D7: profit | O7: 2017 | P7: 93439.27 | R7: =O7 -> 2017 | S7: =P7 -> 93439.27
B8: {=_xlfn.UNIQUE('Sample - Superstore'!H2:H9995)} -> Consumer | C8: =SUMIFS('Sample - Superstore'!$R$2:$R$9995,'Sample - Superstore'!$H$2:$H$9995,'sales and profit by segment'!B8) -> 1161401.3 | D8: =SUMIFS('Sample - Superstore'!$U$2:$U$9995,'Sample - Superstore'!$H$2:$H$9995,'sales and profit by segment'!B8) -> 134119.21 | O8: Grand Total | P8: 286397.02
B9: Corporate | C9: =SUMIFS('Sample - Superstore'!$R$2:$R$9995,'Sample - Superstore'!$H$2:$H$9995,'sales and profit by segment'!B9) -> 706146.37 | D9: =SUMIFS('Sample - Superstore'!$U$2:$U$9995,'Sample - Superstore'!$H$2:$H$9995,'sales and profit by segment'!B9) -> 91979.134
B10: Home Office | C10: =SUMIFS('Sample - Superstore'!$R$2:$R$9995,'Sample - Superstore'!$H$2:$H$9995,'sales and profit by segment'!B10) -> 429653.15 | D10: =SUMIFS('Sample - Superstore'!$U$2:$U$9995,'Sample - Superstore'!$H$2:$H$9995,'sales and profit by segment'!B10) -> 60298.679
B24: Row Labels | C24: Sum of Sales | D24: Sum of Profit | G24: Sales | H24: Profit
B25: Consumer | C25: 1161401.3 | D25: 134119.21 | F25: =B25 -> Consumer | G25: =C25 -> 1161401.3 | H25: =D25 -> 134119.21
B26: Corporate | C26: 706146.37 | D26: 91979.134 | F26: =B26 -> Corporate | G26: =C26 -> 706146.37 | H26: =D26 -> 91979.134
B27: Home Office | C27: 429653.15 | D27: 60298.679 | F27: =B27 -> Home Office | G27: =C27 -> 429653.15 | H27: =D27 -> 60298.679
B28: Grand Total | C28: 2297200.9 | D28: 286397.02

Sheet profit margin by sales subcateg
A2: subcategory | B2: sales | C2: profit | D2: profit margin
A3: {=_xlfn.UNIQUE('Sample - Superstore'!P2:P9995)} -> Bookcases | B3: =SUMIFS('Sample - Superstore'!$R$2:$R$9995,'Sample - Superstore'!$P$2:$P$9995,'profit margin by sales subcateg'!A3) -> 114880 | C3: =SUMIFS('Sample - Superstore'!$U$2:$U$9995,'Sample - Superstore'!$P$2:$P$9995,'profit margin by sales subcateg'!A3) -> -3472.556 | D3: =C3/B3 -> -0.030227682
A4: Chairs | B4: =SUMIFS('Sample - Superstore'!$R$2:$R$9995,'Sample - Superstore'!$P$2:$P$9995,'profit margin by sales subcateg'!A4) -> 328449.1 | C4: =SUMIFS('Sample - Superstore'!$U$2:$U$9995,'Sample - Superstore'!$P$2:$P$9995,'profit margin by sales subcateg'!A4) -> 26590.166 | D4: =C4/B4 -> 0.080956733
A5: Labels | B5: =SUMIFS('Sample - Superstore'!$R$2:$R$9995,'Sample - Superstore'!$P$2:$P$9995,'profit margin by sales subcateg'!A5) -> 12486.312 | C5: =SUMIFS('Sample - Superstore'!$U$2:$U$9995,'Sample - Superstore'!$P$2:$P$9995,'profit margin by sales subcateg'!A5) -> 5546.254 | D5: =C5/B5 -> 0.44418672
A6: Tables | B6: =SUMIFS('Sample - Superstore'!$R$2:$R$9995,'Sample - Superstore'!$P$2:$P$9995,'profit margin by sales subcateg'!A6) -> 206965.53 | C6: =SUMIFS('Sample - Superstore'!$U$2:$U$9995,'Sample - Superstore'!$P$2:$P$9995,'profit margin by sales subcateg'!A6) -> -17725.481 | D6: =C6/B6 -> -0.085644604
A7: Storage | B7: =SUMIFS('Sample - Superstore'!$R$2:$R$9995,'Sample - Superstore'!$P$2:$P$9995,'profit margin by sales subcateg'!A7) -> 223843.61 | C7: =SUMIFS('Sample - Superstore'!$U$2:$U$9995,'Sample - Superstore'!$P$2:$P$9995,'profit margin by sales subcateg'!A7) -> 21278.826 | D7: =C7/B7 -> 0.09506113
A8: Furnishings | B8: =SUMIFS('Sample - Superstore'!$R$2:$R$9995,'Sample - Superstore'!$P$2:$P$9995,'profit margin by sales subcateg'!A8) -> 91705.164 | C8: =SUMIFS('Sample - Superstore'!$U$2:$U$9995,'Sample - Superstore'!$P$2:$P$9995,'profit margin by sales subcateg'!A8) -> 13059.144 | D8: =C8/B8 -> 0.14240358
A9: Art | B9: =SUMIFS('Sample - Superstore'!$R$2:$R$9995,'Sample - Superstore'!$P$2:$P$9995,'profit margin by sales subcateg'!A9) -> 27118.792 | C9: =SUMIFS('Sample - Superstore'!$U$2:$U$9995,'Sample - Superstore'!$P$2:$P$9995,'profit margin by sales subcateg'!A9) -> 6527.787 | D9: =C9/B9 -> 0.24071083
A10: Phones | B10: =SUMIFS('Sample - Superstore'!$R$2:$R$9995,'Sample - Superstore'!$P$2:$P$9995,'profit margin by sales subcateg'!A10) -> 330007.05 | C10: =SUMIFS('Sample - Superstore'!$U$2:$U$9995,'Sample - Superstore'!$P$2:$P$9995,'profit margin by sales subcateg'!A10) -> 44515.731 | D10: =C10/B10 -> 0.13489327
A11: Binders | B11: =SUMIFS('Sample - Superstore'!$R$2:$R$9995,'Sample - Superstore'!$P$2:$P$9995,'profit margin by sales subcateg'!A11) -> 203412.73 | C11: =SUMIFS('Sample - Superstore'!$U$2:$U$9995,'Sample - Superstore'!$P$2:$P$9995,'profit margin by sales subcateg'!A11) -> 30221.763 | D11: =C11/B11 -> 0.14857361
A12: Appliances | B12: =SUMIFS('Sample - Superstore'!$R$2:$R$9995,'Sample - Superstore'!$P$2:$P$9995,'profit margin by sales subcateg'!A12) -> 107532.16 | C12: =SUMIFS('Sample - Superstore'!$U$2:$U$9995,'Sample - Superstore'!$P$2:$P$9995,'profit margin by sales subcateg'!A12) -> 18138.005 | D12: =C12/B12 -> 0.16867517
A13: Paper | B13: =SUMIFS('Sample - Superstore'!$R$2:$R$9995,'Sample - Superstore'!$P$2:$P$9995,'profit margin by sales subcateg'!A13) -> 78479.206 | C13: =SUMIFS('Sample - Superstore'!$U$2:$U$9995,'Sample - Superstore'!$P$2:$P$9995,'profit margin by sales subcateg'!A13) -> 34053.569 | D13: =C13/B13 -> 0.43391837
A14: Accessories | B14: =SUMIFS('Sample - Superstore'!$R$2:$R$9995,'Sample - Superstore'!$P$2:$P$9995,'profit margin by sales subcateg'!A14) -> 167380.32 | C14: =SUMIFS('Sample - Superstore'!$U$2:$U$9995,'Sample - Superstore'!$P$2:$P$9995,'profit margin by sales subcateg'!A14) -> 41936.636 | D14: =C14/B14 -> 0.250547
A15: Envelopes | B15: =SUMIFS('Sample - Superstore'!$R$2:$R$9995,'Sample - Superstore'!$P$2:$P$9995,'profit margin by sales subcateg'!A15) -> 16476.402 | C15: =SUMIFS('Sample - Superstore'!$U$2:$U$9995,'Sample - Superstore'!$P$2:$P$9995,'profit margin by sales subcateg'!A15) -> 6964.1767 | D15: =C15/B15 -> 0.42267582
... A19: Copiers | B19: =SUMIFS('Sample - Superstore'!$R$2:$R$9995,'Sample - Superstore'!$P$2:$P$9995,'profit margin by sales subcateg'!A19) -> 149528.03 | C19: =SUMIFS('Sample - Superstore'!$U$2:$U$9995,'Sample - Superstore'!$P$2:$P$9995,'profit margin by sales subcateg'!A19) -> 55617.825 | D19: =C19/B19 -> 0.37195585
A25: Row Labels | B25: Sum of Profit | C25: Sum of Sales | E25: subcategory | F25: sales | G25: profit | H25: profit margin
A26: Accessories | B26: 41936.636 | C26: 167380.32 | E26: =A26 -> Accessories | F26: =B26 -> 41936.636 | G26: =C26 -> 167380.32 | H26: =F26/G26 -> 0.250547
A27: Appliances | B27: 18138.005 | C27: 107532.16 | E27: =A27 -> Appliances | F27: =B27 -> 18138.005 | G27: =C27 -> 107532.16 | H27: =F27/G27 -> 0.16867517
A28: Art | B28: 6527.787 | C28: 27118.792 | E28: =A28 -> Art | F28: =B28 -> 6527.787 | G28: =C28 -> 27118.792 | H28: =F28/G28 -> 0.24071083
A29: Binders | B29: 30221.763 | C29: 203412.73 | E29: =A29 -> Binders | F29: =B29 -> 30221.763 | G29: =C29 -> 203412.73 | H29: =F29/G29 -> 0.14857361
A30: Bookcases | B30: -3472.556 | C30: 114880 | E30: =A30 -> Bookcases | F30: =B30 -> -3472.556 | G30: =C30 -> 114880 | H30: =F30/G30 -> -0.030227682
A31: Chairs | B31: 26590.166 | C31: 328449.1 | E31: =A31 -> Chairs | F31: =B31 -> 26590.166 | G31: =C31 -> 328449.1 | H31: =F31/G31 -> 0.080956733
A32: Copiers | B32: 55617.825 | C32: 149528.03 | E32: =A32 -> Copiers | F32: =B32 -> 55617.825 | G32: =C32 -> 149528.03 | H32: =F32/G32 -> 0.37195585
A33: Envelopes | B33: 6964.1767 | C33: 16476.402 | E33: =A33 -> Envelopes | F33: =B33 -> 6964.1767 | G33: =C33 -> 16476.402 | H33: =F33/G33 -> 0.42267582
A34: Fasteners | B34: 949.5182 | C34: 3024.28 | E34: =A34 -> Fasteners | F34: =B34 -> 949.5182 | G34: =C34 -> 3024.28 | H34: =F34/G34 -> 0.31396504
A35: Furnishings | B35: 13059.144 | C35: 91705.164 | E35: =A35 -> Furnishings | F35: =B35 -> 13059.144 | G35: =C35 -> 91705.164 | H35: =F35/G35 -> 0.14240358
A36: Labels | B36: 5546.254 | C36: 12486.312 | E36: =A36 -> Labels | F36: =B36 -> 5546.254 | G36: =C36 -> 12486.312 | H36: =F36/G36 -> 0.44418672
A37: Machines | B37: 3384.7569 | C37: 189238.63 | E37: =A37 -> Machines | F37: =B37 -> 3384.7569 | G37: =C37 -> 189238.63 | H37: =F37/G37 -> 0.017886184
... A42: Tables | B42: -17725.481 | C42: 206965.53 | E42: =A42 -> Tables | F42: =B42 -> -17725.481 | G42: =C42 -> 206965.53 | H42: =F42/G42 -> -0.085644604
A43: Grand Total | B43: 286397.02 | C43: 2297200.9
